// class version 52.0 (52)
// access flags 0x21
public class codechicken/nei/guihook/GuiContainerManager {

  // compiled from: GuiContainerManager.java
  // access flags 0xA
  private static INNERCLASS codechicken/nei/guihook/GuiContainerManager$ResourcePackReloaded codechicken/nei/guihook/GuiContainerManager ResourcePackReloaded
  // access flags 0x1008
  static synthetic INNERCLASS codechicken/nei/guihook/GuiContainerManager$1 null null
  // access flags 0x609
  public static abstract INNERCLASS java/util/Map$Entry java/util/Map Entry
  // access flags 0x609
  public static abstract INNERCLASS codechicken/lib/gui/GuiDraw$ITooltipLineHandler codechicken/lib/gui/GuiDraw ITooltipLineHandler
  // access flags 0x19
  public final static INNERCLASS java/lang/invoke/MethodHandles$Lookup java/lang/invoke/MethodHandles Lookup

  // access flags 0x1
  public Lnet/minecraft/client/gui/inventory/GuiContainer; window

  // access flags 0x9
  public static Lnet/minecraft/client/renderer/entity/RenderItem; drawItems

  // access flags 0x19
  // signature Ljava/util/LinkedList<Lcodechicken/nei/guihook/IContainerTooltipHandler;>;
  // declaration: java.util.LinkedList<codechicken.nei.guihook.IContainerTooltipHandler>
  public final static Ljava/util/LinkedList; tooltipHandlers

  // access flags 0x19
  // signature Ljava/util/LinkedList<Lcodechicken/nei/guihook/IContainerInputHandler;>;
  // declaration: java.util.LinkedList<codechicken.nei.guihook.IContainerInputHandler>
  public final static Ljava/util/LinkedList; inputHandlers

  // access flags 0x19
  // signature Ljava/util/LinkedList<Lcodechicken/nei/guihook/IContainerDrawHandler;>;
  // declaration: java.util.LinkedList<codechicken.nei.guihook.IContainerDrawHandler>
  public final static Ljava/util/LinkedList; drawHandlers

  // access flags 0x19
  // signature Ljava/util/LinkedList<Lcodechicken/nei/guihook/IContainerObjectHandler;>;
  // declaration: java.util.LinkedList<codechicken.nei.guihook.IContainerObjectHandler>
  public final static Ljava/util/LinkedList; objectHandlers

  // access flags 0x19
  // signature Ljava/util/LinkedList<Lcodechicken/nei/guihook/IContainerSlotClickHandler;>;
  // declaration: java.util.LinkedList<codechicken.nei.guihook.IContainerSlotClickHandler>
  public final static Ljava/util/LinkedList; slotClickHandlers

  // access flags 0xA
  private static I modelviewDepth

  // access flags 0x1A
  // signature Ljava/util/HashSet<Ljava/lang/String;>;
  // declaration: java.util.HashSet<java.lang.String>
  private final static Ljava/util/HashSet; stackTraces

  // access flags 0x1A
  private final static Lcodechicken/nei/ItemStackSet; renderingErrorItems

  // access flags 0x2
  private I clickHandled

  // access flags 0x11
  // signature Ljava/util/List<Lcodechicken/nei/guihook/IContainerTooltipHandler;>;
  // declaration: java.util.List<codechicken.nei.guihook.IContainerTooltipHandler>
  public final Ljava/util/List; instanceTooltipHandlers

  // access flags 0xA
  private static I tooltipPage

  // access flags 0x9
  public static getManager()Lcodechicken/nei/guihook/GuiContainerManager;
   L0
    LINENUMBER 79 L0
    INVOKESTATIC net/minecraft/client/Minecraft.getMinecraft ()Lnet/minecraft/client/Minecraft;
    GETFIELD net/minecraft/client/Minecraft.currentScreen : Lnet/minecraft/client/gui/GuiScreen;
    ASTORE 0
   L1
    LINENUMBER 80 L1
    ALOAD 0
    INSTANCEOF net/minecraft/client/gui/inventory/GuiContainer
    IFEQ L2
    ALOAD 0
    CHECKCAST net/minecraft/client/gui/inventory/GuiContainer
    INVOKESTATIC codechicken/nei/guihook/GuiContainerManager.getManager (Lnet/minecraft/client/gui/inventory/GuiContainer;)Lcodechicken/nei/guihook/GuiContainerManager;
    GOTO L3
   L2
   FRAME FULL [net/minecraft/client/gui/GuiScreen] []
    ACONST_NULL
   L3
   FRAME FULL [net/minecraft/client/gui/GuiScreen] [codechicken/nei/guihook/GuiContainerManager]
    ARETURN
   L4
    LOCALVARIABLE gui Lnet/minecraft/client/gui/GuiScreen; L1 L4 0
    MAXSTACK = 1
    MAXLOCALS = 1

  // access flags 0x9
  public static getManager(Lnet/minecraft/client/gui/inventory/GuiContainer;)Lcodechicken/nei/guihook/GuiContainerManager;
    ALOAD 0
    GETFIELD net/minecraft/client/gui/inventory/GuiContainer.manager : Lcodechicken/nei/guihook/GuiContainerManager;
    ARETURN
    MAXSTACK = 1
    MAXLOCALS = 1

  // access flags 0x9
  public static addTooltipHandler(Lcodechicken/nei/guihook/IContainerTooltipHandler;)V
   L0
    LINENUMBER 94 L0
    GETSTATIC codechicken/nei/guihook/GuiContainerManager.tooltipHandlers : Ljava/util/LinkedList;
    ALOAD 0
    INVOKEVIRTUAL java/util/LinkedList.add (Ljava/lang/Object;)Z
    POP
   L1
    LINENUMBER 95 L1
    RETURN
   L2
    LOCALVARIABLE handler Lcodechicken/nei/guihook/IContainerTooltipHandler; L0 L2 0
    MAXSTACK = 2
    MAXLOCALS = 1

  // access flags 0x9
  public static addInputHandler(Lcodechicken/nei/guihook/IContainerInputHandler;)V
   L0
    LINENUMBER 103 L0
    GETSTATIC codechicken/nei/guihook/GuiContainerManager.inputHandlers : Ljava/util/LinkedList;
    ALOAD 0
    INVOKEVIRTUAL java/util/LinkedList.add (Ljava/lang/Object;)Z
    POP
   L1
    LINENUMBER 104 L1
    RETURN
   L2
    LOCALVARIABLE handler Lcodechicken/nei/guihook/IContainerInputHandler; L0 L2 0
    MAXSTACK = 2
    MAXLOCALS = 1

  // access flags 0x9
  public static addDrawHandler(Lcodechicken/nei/guihook/IContainerDrawHandler;)V
   L0
    LINENUMBER 112 L0
    GETSTATIC codechicken/nei/guihook/GuiContainerManager.drawHandlers : Ljava/util/LinkedList;
    ALOAD 0
    INVOKEVIRTUAL java/util/LinkedList.add (Ljava/lang/Object;)Z
    POP
   L1
    LINENUMBER 113 L1
    RETURN
   L2
    LOCALVARIABLE handler Lcodechicken/nei/guihook/IContainerDrawHandler; L0 L2 0
    MAXSTACK = 2
    MAXLOCALS = 1

  // access flags 0x9
  public static addObjectHandler(Lcodechicken/nei/guihook/IContainerObjectHandler;)V
   L0
    LINENUMBER 121 L0
    GETSTATIC codechicken/nei/guihook/GuiContainerManager.objectHandlers : Ljava/util/LinkedList;
    ALOAD 0
    INVOKEVIRTUAL java/util/LinkedList.add (Ljava/lang/Object;)Z
    POP
   L1
    LINENUMBER 122 L1
    RETURN
   L2
    LOCALVARIABLE handler Lcodechicken/nei/guihook/IContainerObjectHandler; L0 L2 0
    MAXSTACK = 2
    MAXLOCALS = 1

  // access flags 0x9
  public static addSlotClickHandler(Lcodechicken/nei/guihook/IContainerSlotClickHandler;)V
   L0
    LINENUMBER 131 L0
    GETSTATIC codechicken/nei/guihook/GuiContainerManager.slotClickHandlers : Ljava/util/LinkedList;
    ALOAD 0
    INVOKEVIRTUAL java/util/LinkedList.addFirst (Ljava/lang/Object;)V
   L1
    LINENUMBER 132 L1
    RETURN
   L2
    LOCALVARIABLE handler Lcodechicken/nei/guihook/IContainerSlotClickHandler; L0 L2 0
    MAXSTACK = 2
    MAXLOCALS = 1

  // access flags 0x9
  public static getFontRenderer(Lnet/minecraft/item/ItemStack;)Lnet/minecraft/client/gui/FontRenderer;
   L0
    LINENUMBER 135 L0
    ALOAD 0
    IFNULL L1
    ALOAD 0
    INVOKEVIRTUAL net/minecraft/item/ItemStack.getItem ()Lnet/minecraft/item/Item;
    IFNULL L1
   L2
    LINENUMBER 136 L2
    ALOAD 0
    INVOKEVIRTUAL net/minecraft/item/ItemStack.getItem ()Lnet/minecraft/item/Item;
    ALOAD 0
    INVOKEVIRTUAL net/minecraft/item/Item.getFontRenderer (Lnet/minecraft/item/ItemStack;)Lnet/minecraft/client/gui/FontRenderer;
    ASTORE 1
   L3
    LINENUMBER 137 L3
    ALOAD 1
    IFNULL L1
    ALOAD 1
    ARETURN
   L1
    LINENUMBER 139 L1
   FRAME FULL [net/minecraft/item/ItemStack] []
    GETSTATIC codechicken/lib/gui/GuiDraw.fontRenderer : Lnet/minecraft/client/gui/FontRenderer;
    ARETURN
   L4
    LOCALVARIABLE f Lnet/minecraft/client/gui/FontRenderer; L3 L1 1
    LOCALVARIABLE stack Lnet/minecraft/item/ItemStack; L0 L4 0
    MAXSTACK = 2
    MAXLOCALS = 2

  // access flags 0x9
  // signature (Lnet/minecraft/item/ItemStack;Lnet/minecraft/client/gui/inventory/GuiContainer;Z)Ljava/util/List<Ljava/lang/String;>;
  // declaration: java.util.List<java.lang.String> itemDisplayNameMultiline(net.minecraft.item.ItemStack, net.minecraft.client.gui.inventory.GuiContainer, boolean)
  public static itemDisplayNameMultiline(Lnet/minecraft/item/ItemStack;Lnet/minecraft/client/gui/inventory/GuiContainer;Z)Ljava/util/List;
    TRYCATCHBLOCK L0 L1 L2 java/lang/Throwable
   L3
    LINENUMBER 153 L3
    ACONST_NULL
    ASTORE 3
   L0
    LINENUMBER 155 L0
    ALOAD 0
   L4
    LINENUMBER 156 L4
    INVOKESTATIC net/minecraft/client/Minecraft.getMinecraft ()Lnet/minecraft/client/Minecraft;
    GETFIELD net/minecraft/client/Minecraft.thePlayer : Lnet/minecraft/client/entity/EntityClientPlayerMP;
    ILOAD 2
    IFEQ L5
   L6
    LINENUMBER 157 L6
    INVOKESTATIC net/minecraft/client/Minecraft.getMinecraft ()Lnet/minecraft/client/Minecraft;
    GETFIELD net/minecraft/client/Minecraft.gameSettings : Lnet/minecraft/client/settings/GameSettings;
    GETFIELD net/minecraft/client/settings/GameSettings.advancedItemTooltips : Z
    IFEQ L5
    ICONST_1
    GOTO L7
   L5
   FRAME FULL [net/minecraft/item/ItemStack net/minecraft/client/gui/inventory/GuiContainer I N] [net/minecraft/item/ItemStack net/minecraft/client/entity/EntityClientPlayerMP]
    ICONST_0
   L7
    LINENUMBER 155 L7
   FRAME FULL [net/minecraft/item/ItemStack net/minecraft/client/gui/inventory/GuiContainer I N] [net/minecraft/item/ItemStack net/minecraft/client/entity/EntityClientPlayerMP I]
    INVOKEVIRTUAL net/minecraft/item/ItemStack.getTooltip (Lnet/minecraft/entity/player/EntityPlayer;Z)Ljava/util/List;
    ASTORE 3
   L1
    LINENUMBER 160 L1
    GOTO L8
   L2
    LINENUMBER 158 L2
   FRAME FULL [net/minecraft/item/ItemStack net/minecraft/client/gui/inventory/GuiContainer I java/util/List] [java/lang/Throwable]
    ASTORE 4
   L9
    LINENUMBER 159 L9
    NEW java/util/ArrayList
    DUP
    INVOKESPECIAL java/util/ArrayList.<init> ()V
    ASTORE 3
   L8
    LINENUMBER 162 L8
   FRAME FULL [net/minecraft/item/ItemStack net/minecraft/client/gui/inventory/GuiContainer I java/util/List] []
    ALOAD 3
    INVOKEINTERFACE java/util/List.isEmpty ()Z
    IFEQ L10
   L11
    LINENUMBER 163 L11
    ALOAD 3
    LDC "Unnamed"
    INVOKEINTERFACE java/util/List.add (Ljava/lang/Object;)Z
    POP
    GOTO L12
   L10
    LINENUMBER 164 L10
   FRAME FULL [net/minecraft/item/ItemStack net/minecraft/client/gui/inventory/GuiContainer I java/util/List] []
    ALOAD 3
    ICONST_0
    INVOKEINTERFACE java/util/List.get (I)Ljava/lang/Object;
    IFNULL L13
    ALOAD 3
    ICONST_0
    INVOKEINTERFACE java/util/List.get (I)Ljava/lang/Object;
    CHECKCAST java/lang/String
    INVOKEVIRTUAL java/lang/String.isEmpty ()Z
    IFEQ L12
   L13
    LINENUMBER 165 L13
   FRAME FULL [net/minecraft/item/ItemStack net/minecraft/client/gui/inventory/GuiContainer I java/util/List] []
    ALOAD 3
    ICONST_0
    LDC "Unnamed"
    INVOKEINTERFACE java/util/List.set (ILjava/lang/Object;)Ljava/lang/Object;
    POP
   L12
    LINENUMBER 168 L12
   FRAME FULL [net/minecraft/item/ItemStack net/minecraft/client/gui/inventory/GuiContainer I java/util/List] []
    ILOAD 2
    IFEQ L14
   L15
    LINENUMBER 169 L15
    GETSTATIC codechicken/nei/guihook/GuiContainerManager.tooltipHandlers : Ljava/util/LinkedList;
    INVOKEVIRTUAL java/util/LinkedList.iterator ()Ljava/util/Iterator;
    ASTORE 4
   L16
   FRAME FULL [net/minecraft/item/ItemStack net/minecraft/client/gui/inventory/GuiContainer I java/util/List java/util/Iterator] []
    ALOAD 4
    INVOKEINTERFACE java/util/Iterator.hasNext ()Z
    IFEQ L14
    ALOAD 4
    INVOKEINTERFACE java/util/Iterator.next ()Ljava/lang/Object;
    CHECKCAST codechicken/nei/guihook/IContainerTooltipHandler
    ASTORE 5
   L17
    LINENUMBER 170 L17
    ALOAD 5
    ALOAD 1
    ALOAD 0
    ALOAD 3
    INVOKEINTERFACE codechicken/nei/guihook/IContainerTooltipHandler.handleItemDisplayName (Lnet/minecraft/client/gui/inventory/GuiContainer;Lnet/minecraft/item/ItemStack;Ljava/util/List;)Ljava/util/List;
    ASTORE 3
   L18
    LINENUMBER 171 L18
    GOTO L16
   L14
    LINENUMBER 174 L14
   FRAME FULL [net/minecraft/item/ItemStack net/minecraft/client/gui/inventory/GuiContainer I java/util/List] []
    ALOAD 3
    ICONST_0
    NEW java/lang/StringBuilder
    DUP
    INVOKESPECIAL java/lang/StringBuilder.<init> ()V
    ALOAD 0
    INVOKEVIRTUAL net/minecraft/item/ItemStack.getRarity ()Lnet/minecraft/item/EnumRarity;
    GETFIELD net/minecraft/item/EnumRarity.rarityColor : Lnet/minecraft/util/EnumChatFormatting;
    INVOKEVIRTUAL net/minecraft/util/EnumChatFormatting.toString ()Ljava/lang/String;
    INVOKEVIRTUAL java/lang/StringBuilder.append (Ljava/lang/String;)Ljava/lang/StringBuilder;
    ALOAD 3
    ICONST_0
    INVOKEINTERFACE java/util/List.get (I)Ljava/lang/Object;
    CHECKCAST java/lang/String
    INVOKEVIRTUAL java/lang/StringBuilder.append (Ljava/lang/String;)Ljava/lang/StringBuilder;
    INVOKEVIRTUAL java/lang/StringBuilder.toString ()Ljava/lang/String;
    INVOKEINTERFACE java/util/List.set (ILjava/lang/Object;)Ljava/lang/Object;
    POP
   L19
    LINENUMBER 176 L19
    ICONST_1
    ISTORE 4
   L20
   FRAME FULL [net/minecraft/item/ItemStack net/minecraft/client/gui/inventory/GuiContainer I java/util/List I] []
    ILOAD 4
    ALOAD 3
    INVOKEINTERFACE java/util/List.size ()I
    IF_ICMPGE L21
   L22
    LINENUMBER 177 L22
    ALOAD 3
    ILOAD 4
    NEW java/lang/StringBuilder
    DUP
    INVOKESPECIAL java/lang/StringBuilder.<init> ()V
    GETSTATIC net/minecraft/util/EnumChatFormatting.GRAY : Lnet/minecraft/util/EnumChatFormatting;
    INVOKEVIRTUAL java/lang/StringBuilder.append (Ljava/lang/Object;)Ljava/lang/StringBuilder;
    ALOAD 3
    ILOAD 4
    INVOKEINTERFACE java/util/List.get (I)Ljava/lang/Object;
    CHECKCAST java/lang/String
    INVOKEVIRTUAL java/lang/StringBuilder.append (Ljava/lang/String;)Ljava/lang/StringBuilder;
    GETSTATIC net/minecraft/util/EnumChatFormatting.RESET : Lnet/minecraft/util/EnumChatFormatting;
    INVOKEVIRTUAL java/lang/StringBuilder.append (Ljava/lang/Object;)Ljava/lang/StringBuilder;
    INVOKEVIRTUAL java/lang/StringBuilder.toString ()Ljava/lang/String;
    INVOKEINTERFACE java/util/List.set (ILjava/lang/Object;)Ljava/lang/Object;
    POP
   L23
    LINENUMBER 176 L23
    IINC 4 1
    GOTO L20
   L21
    LINENUMBER 180 L21
   FRAME FULL [net/minecraft/item/ItemStack net/minecraft/client/gui/inventory/GuiContainer I java/util/List I] []
    ALOAD 3
    ARETURN
   L24
    LOCALVARIABLE ignored Ljava/lang/Throwable; L9 L8 4
    LOCALVARIABLE handler Lcodechicken/nei/guihook/IContainerTooltipHandler; L17 L18 5
    LOCALVARIABLE i I L20 L21 4
    LOCALVARIABLE stack Lnet/minecraft/item/ItemStack; L3 L24 0
    LOCALVARIABLE gui Lnet/minecraft/client/gui/inventory/GuiContainer; L3 L24 1
    LOCALVARIABLE includeHandlers Z L3 L24 2
    LOCALVARIABLE namelist Ljava/util/List; L0 L24 3
    // signature Ljava/util/List<Ljava/lang/String;>;
    // declaration: java.util.List<java.lang.String>
    MAXSTACK = 5
    MAXLOCALS = 6

  // access flags 0x9
  public static countDetails(IILjava/lang/String;Ljava/lang/String;)Ljava/lang/String;
  @Ljavax/annotation/Nullable;()
   L0
    LINENUMBER 185 L0
    ILOAD 1
    ICONST_1
    IF_ICMPLE L1
    ILOAD 0
    ILOAD 1
    IF_ICMPLE L1
   L2
    LINENUMBER 186 L2
    ILOAD 0
    ILOAD 1
    IREM
    ISTORE 4
   L3
    LINENUMBER 188 L3
    ILOAD 4
    IFLE L4
   L5
    LINENUMBER 189 L5
    ALOAD 2
    ICONST_4
    ANEWARRAY java/lang/Object
    DUP
    ICONST_0
    ILOAD 0
    I2L
   L6
    LINENUMBER 191 L6
    INVOKESTATIC codechicken/nei/NEIClientUtils.formatNumbers (J)Ljava/lang/String;
    AASTORE
    DUP
    ICONST_1
    ILOAD 0
    ILOAD 1
    IDIV
    I2L
   L7
    LINENUMBER 192 L7
    INVOKESTATIC codechicken/nei/NEIClientUtils.formatNumbers (J)Ljava/lang/String;
    AASTORE
    DUP
    ICONST_2
    ILOAD 1
    I2L
   L8
    LINENUMBER 193 L8
    INVOKESTATIC codechicken/nei/NEIClientUtils.formatNumbers (J)Ljava/lang/String;
    AASTORE
    DUP
    ICONST_3
    ILOAD 4
    I2L
   L9
    LINENUMBER 194 L9
    INVOKESTATIC codechicken/nei/NEIClientUtils.formatNumbers (J)Ljava/lang/String;
    AASTORE
   L10
    LINENUMBER 189 L10
    INVOKESTATIC java/lang/String.format (Ljava/lang/String;[Ljava/lang/Object;)Ljava/lang/String;
    ARETURN
   L4
    LINENUMBER 196 L4
   FRAME FULL [I I java/lang/String java/lang/String I] []
    ALOAD 3
    ICONST_3
    ANEWARRAY java/lang/Object
    DUP
    ICONST_0
    ILOAD 0
    I2L
   L11
    LINENUMBER 198 L11
    INVOKESTATIC codechicken/nei/NEIClientUtils.formatNumbers (J)Ljava/lang/String;
    AASTORE
    DUP
    ICONST_1
    ILOAD 0
    ILOAD 1
    IDIV
    I2L
   L12
    LINENUMBER 199 L12
    INVOKESTATIC codechicken/nei/NEIClientUtils.formatNumbers (J)Ljava/lang/String;
    AASTORE
    DUP
    ICONST_2
    ILOAD 1
    I2L
   L13
    LINENUMBER 200 L13
    INVOKESTATIC codechicken/nei/NEIClientUtils.formatNumbers (J)Ljava/lang/String;
    AASTORE
   L14
    LINENUMBER 196 L14
    INVOKESTATIC java/lang/String.format (Ljava/lang/String;[Ljava/lang/Object;)Ljava/lang/String;
    ARETURN
   L1
    LINENUMBER 204 L1
   FRAME FULL [I I java/lang/String java/lang/String] []
    ACONST_NULL
    ARETURN
   L15
    LOCALVARIABLE remainder I L3 L1 4
    LOCALVARIABLE stackSize I L0 L15 0
    LOCALVARIABLE maxStackSize I L0 L15 1
    LOCALVARIABLE fullPattern Ljava/lang/String; L0 L15 2
    LOCALVARIABLE shortPattern Ljava/lang/String; L0 L15 3
    MAXSTACK = 6
    MAXLOCALS = 5

  // access flags 0x9
  public static itemCountDetails(Lnet/minecraft/item/ItemStack;)Ljava/lang/String;
  @Ljavax/annotation/Nullable;()
   L0
    LINENUMBER 209 L0
    ALOAD 0
    INVOKESTATIC codechicken/nei/recipe/StackInfo.getFluid (Lnet/minecraft/item/ItemStack;)Lnet/minecraftforge/fluids/FluidStack;
    ASTORE 1
   L1
    LINENUMBER 210 L1
    ALOAD 1
    IFNULL L2
   L3
    LINENUMBER 211 L3
    ALOAD 1
    GETFIELD net/minecraftforge/fluids/FluidStack.amount : I
    ICONST_1
    ALOAD 0
    GETFIELD net/minecraft/item/ItemStack.stackSize : I
    INVOKESTATIC java/lang/Math.max (II)I
    IMUL
    INVOKESTATIC codechicken/nei/guihook/GuiContainerManager.fluidAmountDetails (I)Ljava/lang/String;
    ARETURN
   L2
    LINENUMBER 213 L2
   FRAME FULL [net/minecraft/item/ItemStack net/minecraftforge/fluids/FluidStack] []
    ALOAD 0
    GETFIELD net/minecraft/item/ItemStack.stackSize : I
    ALOAD 0
   L4
    LINENUMBER 215 L4
    INVOKEVIRTUAL net/minecraft/item/ItemStack.getMaxStackSize ()I
    LDC "Count: %s = %s * %s + %s"
    LDC "Count: %s = %s * %s"
   L5
    LINENUMBER 213 L5
    INVOKESTATIC codechicken/nei/guihook/GuiContainerManager.countDetails (IILjava/lang/String;Ljava/lang/String;)Ljava/lang/String;
    ARETURN
   L6
    LOCALVARIABLE stack Lnet/minecraft/item/ItemStack; L0 L6 0
    LOCALVARIABLE fluid Lnet/minecraftforge/fluids/FluidStack; L1 L6 1
    MAXSTACK = 4
    MAXLOCALS = 2

  // access flags 0x9
  public static fluidAmountDetails(Lnet/minecraftforge/fluids/FluidStack;)Ljava/lang/String;
  @Ljavax/annotation/Nullable;()
   L0
    LINENUMBER 224 L0
    ALOAD 0
    GETFIELD net/minecraftforge/fluids/FluidStack.amount : I
    INVOKESTATIC codechicken/nei/guihook/GuiContainerManager.fluidAmountDetails (I)Ljava/lang/String;
    ARETURN
   L1
    LOCALVARIABLE fluid Lnet/minecraftforge/fluids/FluidStack; L0 L1 0
    MAXSTACK = 1
    MAXLOCALS = 1

  // access flags 0x9
  public static fluidAmountDetails(I)Ljava/lang/String;
  @Ljavax/annotation/Nullable;()
   L0
    LINENUMBER 229 L0
    ILOAD 0
    SIPUSH 144
    LDC "Amount: %s L = %s * %s L + %s L"
    LDC "Amount: %s L = %s * %s L"
    INVOKESTATIC codechicken/nei/guihook/GuiContainerManager.countDetails (IILjava/lang/String;Ljava/lang/String;)Ljava/lang/String;
    ARETURN
   L1
    LOCALVARIABLE amount I L0 L1 0
    MAXSTACK = 4
    MAXLOCALS = 1

  // access flags 0x9
  public static itemDisplayNameShort(Lnet/minecraft/item/ItemStack;)Ljava/lang/String;
    TRYCATCHBLOCK L0 L1 L2 java/lang/Throwable
   L0
    LINENUMBER 241 L0
    ALOAD 0
    INVOKESTATIC net/minecraft/client/Minecraft.getMinecraft ()Lnet/minecraft/client/Minecraft;
    GETFIELD net/minecraft/client/Minecraft.thePlayer : Lnet/minecraft/client/entity/EntityClientPlayerMP;
    ICONST_0
    INVOKEVIRTUAL net/minecraft/item/ItemStack.getTooltip (Lnet/minecraft/entity/player/EntityPlayer;Z)Ljava/util/List;
    ASTORE 1
   L3
    LINENUMBER 243 L3
    ALOAD 1
    INVOKEINTERFACE java/util/List.isEmpty ()Z
    IFNE L4
    LDC ""
    ALOAD 1
    ICONST_0
    INVOKEINTERFACE java/util/List.get (I)Ljava/lang/Object;
    INVOKEVIRTUAL java/lang/String.equals (Ljava/lang/Object;)Z
    IFNE L4
   L5
    LINENUMBER 244 L5
    NEW java/lang/StringBuilder
    DUP
    INVOKESPECIAL java/lang/StringBuilder.<init> ()V
    ALOAD 0
    INVOKEVIRTUAL net/minecraft/item/ItemStack.getRarity ()Lnet/minecraft/item/EnumRarity;
    GETFIELD net/minecraft/item/EnumRarity.rarityColor : Lnet/minecraft/util/EnumChatFormatting;
    INVOKEVIRTUAL net/minecraft/util/EnumChatFormatting.toString ()Ljava/lang/String;
    INVOKEVIRTUAL java/lang/StringBuilder.append (Ljava/lang/String;)Ljava/lang/StringBuilder;
    ALOAD 1
    ICONST_0
    INVOKEINTERFACE java/util/List.get (I)Ljava/lang/Object;
    CHECKCAST java/lang/String
    INVOKEVIRTUAL java/lang/StringBuilder.append (Ljava/lang/String;)Ljava/lang/StringBuilder;
    GETSTATIC net/minecraft/util/EnumChatFormatting.RESET : Lnet/minecraft/util/EnumChatFormatting;
    INVOKEVIRTUAL java/lang/StringBuilder.append (Ljava/lang/Object;)Ljava/lang/StringBuilder;
    INVOKEVIRTUAL java/lang/StringBuilder.toString ()Ljava/lang/String;
   L1
    ARETURN
   L4
    LINENUMBER 247 L4
   FRAME FULL [net/minecraft/item/ItemStack java/util/List] []
    GOTO L6
   L2
   FRAME FULL [net/minecraft/item/ItemStack] [java/lang/Throwable]
    ASTORE 1
   L6
    LINENUMBER 249 L6
   FRAME FULL [net/minecraft/item/ItemStack java/lang/Object] []
    LDC "Unnamed"
    ARETURN
   L7
    LOCALVARIABLE namelist Ljava/util/List; L3 L4 1
    // signature Ljava/util/List<Ljava/lang/String;>;
    // declaration: java.util.List<java.lang.String>
    LOCALVARIABLE itemstack Lnet/minecraft/item/ItemStack; L0 L7 0
    MAXSTACK = 3
    MAXLOCALS = 2

  // DEPRECATED
  // access flags 0x20009
  public static concatenatedDisplayName(Lnet/minecraft/item/ItemStack;Z)Ljava/lang/String;
  @Ljava/lang/Deprecated;()
   L0
    LINENUMBER 261 L0
    ALOAD 0
    ACONST_NULL
    ILOAD 1
    INVOKESTATIC codechicken/nei/guihook/GuiContainerManager.itemDisplayNameMultiline (Lnet/minecraft/item/ItemStack;Lnet/minecraft/client/gui/inventory/GuiContainer;Z)Ljava/util/List;
    ASTORE 2
   L1
    LINENUMBER 262 L1
    NEW java/util/StringJoiner
    DUP
    LDC "#"
    INVOKESPECIAL java/util/StringJoiner.<init> (Ljava/lang/CharSequence;)V
    ASTORE 3
   L2
    LINENUMBER 264 L2
    ALOAD 2
    INVOKEINTERFACE java/util/List.iterator ()Ljava/util/Iterator;
    ASTORE 4
   L3
   FRAME FULL [net/minecraft/item/ItemStack I java/util/List java/util/StringJoiner java/util/Iterator] []
    ALOAD 4
    INVOKEINTERFACE java/util/Iterator.hasNext ()Z
    IFEQ L4
    ALOAD 4
    INVOKEINTERFACE java/util/Iterator.next ()Ljava/lang/Object;
    CHECKCAST java/lang/String
    ASTORE 5
   L5
    LINENUMBER 265 L5
    ALOAD 5
    INVOKEVIRTUAL java/lang/String.isEmpty ()Z
    IFNE L6
   L7
    LINENUMBER 266 L7
    ALOAD 3
    ALOAD 5
    INVOKEVIRTUAL java/util/StringJoiner.add (Ljava/lang/CharSequence;)Ljava/util/StringJoiner;
    POP
   L6
    LINENUMBER 268 L6
   FRAME FULL [net/minecraft/item/ItemStack I java/util/List java/util/StringJoiner java/util/Iterator java/lang/String] []
    GOTO L3
   L4
    LINENUMBER 270 L4
   FRAME FULL [net/minecraft/item/ItemStack I java/util/List java/util/StringJoiner java/util/Iterator] []
    ALOAD 3
    INVOKEVIRTUAL java/util/StringJoiner.toString ()Ljava/lang/String;
    INVOKESTATIC net/minecraft/util/EnumChatFormatting.getTextWithoutFormattingCodes (Ljava/lang/String;)Ljava/lang/String;
    ARETURN
   L8
    LOCALVARIABLE name Ljava/lang/String; L5 L6 5
    LOCALVARIABLE itemstack Lnet/minecraft/item/ItemStack; L0 L8 0
    LOCALVARIABLE includeHandlers Z L0 L8 1
    LOCALVARIABLE list Ljava/util/List; L1 L8 2
    // signature Ljava/util/List<Ljava/lang/String;>;
    // declaration: java.util.List<java.lang.String>
    LOCALVARIABLE sb Ljava/util/StringJoiner; L2 L8 3
    MAXSTACK = 3
    MAXLOCALS = 6

  // access flags 0x9
  public static drawItem(IILnet/minecraft/item/ItemStack;)V
   L0
    LINENUMBER 274 L0
    ILOAD 0
    ILOAD 1
    ALOAD 2
    ICONST_0
    INVOKESTATIC codechicken/nei/guihook/GuiContainerManager.drawItem (IILnet/minecraft/item/ItemStack;Z)V
   L1
    LINENUMBER 275 L1
    RETURN
   L2
    LOCALVARIABLE i I L0 L2 0
    LOCALVARIABLE j I L0 L2 1
    LOCALVARIABLE itemstack Lnet/minecraft/item/ItemStack; L0 L2 2
    MAXSTACK = 4
    MAXLOCALS = 3

  // access flags 0x9
  public static drawItem(IILnet/minecraft/item/ItemStack;Z)V
   L0
    LINENUMBER 278 L0
    ILOAD 0
    ILOAD 1
    ALOAD 2
    ILOAD 3
    ACONST_NULL
    INVOKESTATIC codechicken/nei/guihook/GuiContainerManager.drawItem (IILnet/minecraft/item/ItemStack;ZLjava/lang/String;)V
   L1
    LINENUMBER 279 L1
    RETURN
   L2
    LOCALVARIABLE i I L0 L2 0
    LOCALVARIABLE j I L0 L2 1
    LOCALVARIABLE itemstack Lnet/minecraft/item/ItemStack; L0 L2 2
    LOCALVARIABLE smallAmount Z L0 L2 3
    MAXSTACK = 5
    MAXLOCALS = 4

  // access flags 0x9
  public static drawItem(IILnet/minecraft/item/ItemStack;ZLjava/lang/String;)V
   L0
    LINENUMBER 282 L0
    ILOAD 0
    ILOAD 1
    ALOAD 2
    ALOAD 2
    INVOKESTATIC codechicken/nei/guihook/GuiContainerManager.getFontRenderer (Lnet/minecraft/item/ItemStack;)Lnet/minecraft/client/gui/FontRenderer;
    ILOAD 3
    ALOAD 4
    INVOKESTATIC codechicken/nei/guihook/GuiContainerManager.drawItem (IILnet/minecraft/item/ItemStack;Lnet/minecraft/client/gui/FontRenderer;ZLjava/lang/String;)V
   L1
    LINENUMBER 283 L1
    RETURN
   L2
    LOCALVARIABLE i I L0 L2 0
    LOCALVARIABLE j I L0 L2 1
    LOCALVARIABLE itemstack Lnet/minecraft/item/ItemStack; L0 L2 2
    LOCALVARIABLE smallAmount Z L0 L2 3
    LOCALVARIABLE stackSize Ljava/lang/String; L0 L2 4
    MAXSTACK = 6
    MAXLOCALS = 5

  // access flags 0x9
  public static drawItem(IILnet/minecraft/item/ItemStack;Lnet/minecraft/client/gui/FontRenderer;)V
   L0
    LINENUMBER 286 L0
    ILOAD 0
    ILOAD 1
    ALOAD 2
    ALOAD 3
    ICONST_0
    ACONST_NULL
    INVOKESTATIC codechicken/nei/guihook/GuiContainerManager.drawItem (IILnet/minecraft/item/ItemStack;Lnet/minecraft/client/gui/FontRenderer;ZLjava/lang/String;)V
   L1
    LINENUMBER 287 L1
    RETURN
   L2
    LOCALVARIABLE i I L0 L2 0
    LOCALVARIABLE j I L0 L2 1
    LOCALVARIABLE itemstack Lnet/minecraft/item/ItemStack; L0 L2 2
    LOCALVARIABLE fontRenderer Lnet/minecraft/client/gui/FontRenderer; L0 L2 3
    MAXSTACK = 6
    MAXLOCALS = 4

  // access flags 0x9
  public static drawItem(IILnet/minecraft/item/ItemStack;Lnet/minecraft/client/gui/FontRenderer;ZLjava/lang/String;)V
    TRYCATCHBLOCK L0 L1 L2 java/lang/Exception
   L3
    LINENUMBER 295 L3
    INVOKESTATIC codechicken/nei/guihook/GuiContainerManager.enable3DRender ()V
   L4
    LINENUMBER 297 L4
    LDC 32826
    INVOKESTATIC org/lwjgl/opengl/GL11.glGetBoolean (I)Z
    ISTORE 6
   L5
    LINENUMBER 298 L5
    GETSTATIC codechicken/nei/guihook/GuiContainerManager.drawItems : Lnet/minecraft/client/renderer/entity/RenderItem;
    DUP
    GETFIELD net/minecraft/client/renderer/entity/RenderItem.zLevel : F
    LDC 100.0
    FADD
    DUP_X1
    PUTFIELD net/minecraft/client/renderer/entity/RenderItem.zLevel : F
    FSTORE 7
   L6
    LINENUMBER 300 L6
    GETSTATIC codechicken/nei/guihook/GuiContainerManager.renderingErrorItems : Lcodechicken/nei/ItemStackSet;
    ALOAD 2
    INVOKEVIRTUAL codechicken/nei/ItemStackSet.contains (Lnet/minecraft/item/ItemStack;)Z
    IFNE L7
   L8
    LINENUMBER 301 L8
    ILOAD 4
    IFEQ L9
    LDC 0.5
    GOTO L10
   L9
   FRAME FULL [I I net/minecraft/item/ItemStack net/minecraft/client/gui/FontRenderer I java/lang/String I F] []
    FCONST_1
   L10
   FRAME FULL [I I net/minecraft/item/ItemStack net/minecraft/client/gui/FontRenderer I java/lang/String I F] [F]
    FSTORE 8
   L0
    LINENUMBER 304 L0
    GETSTATIC codechicken/nei/guihook/GuiContainerManager.drawItems : Lnet/minecraft/client/renderer/entity/RenderItem;
    ALOAD 3
    GETSTATIC codechicken/lib/gui/GuiDraw.renderEngine : Lnet/minecraft/client/renderer/texture/TextureManager;
    ALOAD 2
    ILOAD 0
    ILOAD 1
    INVOKEVIRTUAL net/minecraft/client/renderer/entity/RenderItem.renderItemAndEffectIntoGUI (Lnet/minecraft/client/gui/FontRenderer;Lnet/minecraft/client/renderer/texture/TextureManager;Lnet/minecraft/item/ItemStack;II)V
   L11
    LINENUMBER 306 L11
    ALOAD 5
    IFNONNULL L12
   L13
    LINENUMBER 307 L13
    ALOAD 2
    GETFIELD net/minecraft/item/ItemStack.stackSize : I
    ICONST_1
    IF_ICMPLE L14
   L15
    LINENUMBER 308 L15
    GETSTATIC codechicken/nei/util/ReadableNumberConverter.INSTANCE : Lcodechicken/nei/util/ReadableNumberConverter;
    ALOAD 2
    GETFIELD net/minecraft/item/ItemStack.stackSize : I
    I2L
    INVOKEVIRTUAL codechicken/nei/util/ReadableNumberConverter.toWideReadableForm (J)Ljava/lang/String;
    ASTORE 5
   L16
    LINENUMBER 310 L16
    ALOAD 5
    INVOKEVIRTUAL java/lang/String.length ()I
    ICONST_3
    IF_ICMPNE L17
   L18
    LINENUMBER 311 L18
    LDC 0.8
    FSTORE 8
    GOTO L12
   L17
    LINENUMBER 312 L17
   FRAME FULL [I I net/minecraft/item/ItemStack net/minecraft/client/gui/FontRenderer I java/lang/String I F F] []
    ALOAD 5
    INVOKEVIRTUAL java/lang/String.length ()I
    ICONST_4
    IF_ICMPNE L19
   L20
    LINENUMBER 313 L20
    LDC 0.6
    FSTORE 8
    GOTO L12
   L19
    LINENUMBER 314 L19
   FRAME FULL [I I net/minecraft/item/ItemStack net/minecraft/client/gui/FontRenderer I java/lang/String I F F] []
    ALOAD 5
    INVOKEVIRTUAL java/lang/String.length ()I
    ICONST_4
    IF_ICMPLE L12
   L21
    LINENUMBER 315 L21
    LDC 0.5
    FSTORE 8
    GOTO L12
   L14
    LINENUMBER 319 L14
   FRAME FULL [I I net/minecraft/item/ItemStack net/minecraft/client/gui/FontRenderer I java/lang/String I F F] []
    LDC ""
    ASTORE 5
   L12
    LINENUMBER 324 L12
   FRAME FULL [I I net/minecraft/item/ItemStack net/minecraft/client/gui/FontRenderer I java/lang/String I F F] []
    FLOAD 8
    FCONST_1
    FCMPL
    IFEQ L22
   L23
    LINENUMBER 326 L23
    ALOAD 5
    INVOKEVIRTUAL java/lang/String.isEmpty ()Z
    IFNE L24
   L25
    LINENUMBER 327 L25
    ILOAD 0
    ILOAD 1
    ALOAD 5
    FLOAD 8
    INVOKESTATIC codechicken/nei/guihook/GuiContainerManager.drawBigStackSize (IILjava/lang/String;F)V
   L24
    LINENUMBER 331 L24
   FRAME FULL [I I net/minecraft/item/ItemStack net/minecraft/client/gui/FontRenderer I java/lang/String I F F] []
    GETSTATIC codechicken/nei/guihook/GuiContainerManager.drawItems : Lnet/minecraft/client/renderer/entity/RenderItem;
    ALOAD 3
    GETSTATIC codechicken/lib/gui/GuiDraw.renderEngine : Lnet/minecraft/client/renderer/texture/TextureManager;
    ALOAD 2
    ILOAD 0
    ILOAD 1
    LDC ""
    INVOKEVIRTUAL net/minecraft/client/renderer/entity/RenderItem.renderItemOverlayIntoGUI (Lnet/minecraft/client/gui/FontRenderer;Lnet/minecraft/client/renderer/texture/TextureManager;Lnet/minecraft/item/ItemStack;IILjava/lang/String;)V
    GOTO L26
   L22
    LINENUMBER 333 L22
   FRAME FULL [I I net/minecraft/item/ItemStack net/minecraft/client/gui/FontRenderer I java/lang/String I F F] []
    GETSTATIC codechicken/nei/guihook/GuiContainerManager.drawItems : Lnet/minecraft/client/renderer/entity/RenderItem;
    ALOAD 3
    GETSTATIC codechicken/lib/gui/GuiDraw.renderEngine : Lnet/minecraft/client/renderer/texture/TextureManager;
    ALOAD 2
    ILOAD 0
    ILOAD 1
    ALOAD 5
    INVOKEVIRTUAL net/minecraft/client/renderer/entity/RenderItem.renderItemOverlayIntoGUI (Lnet/minecraft/client/gui/FontRenderer;Lnet/minecraft/client/renderer/texture/TextureManager;Lnet/minecraft/item/ItemStack;IILjava/lang/String;)V
   L26
    LINENUMBER 336 L26
   FRAME FULL [I I net/minecraft/item/ItemStack net/minecraft/client/gui/FontRenderer I java/lang/String I F F] []
    INVOKESTATIC codechicken/nei/guihook/GuiContainerManager.checkMatrixStack ()Z
    IFNE L27
    NEW java/lang/IllegalStateException
    DUP
    LDC "Modelview matrix stack too deep"
    INVOKESPECIAL java/lang/IllegalStateException.<init> (Ljava/lang/String;)V
    ATHROW
   L27
    LINENUMBER 337 L27
   FRAME FULL [I I net/minecraft/item/ItemStack net/minecraft/client/gui/FontRenderer I java/lang/String I F F] []
    GETSTATIC net/minecraft/client/renderer/Tessellator.instance : Lnet/minecraft/client/renderer/Tessellator;
    GETFIELD net/minecraft/client/renderer/Tessellator.isDrawing : Z
    IFEQ L1
    NEW java/lang/IllegalStateException
    DUP
    LDC "Still drawing"
    INVOKESPECIAL java/lang/IllegalStateException.<init> (Ljava/lang/String;)V
    ATHROW
   L1
    LINENUMBER 347 L1
   FRAME FULL [I I net/minecraft/item/ItemStack net/minecraft/client/gui/FontRenderer I java/lang/String I F F] []
    GOTO L28
   L2
    LINENUMBER 338 L2
   FRAME FULL [I I net/minecraft/item/ItemStack net/minecraft/client/gui/FontRenderer I java/lang/String I F F] [java/lang/Exception]
    ASTORE 9
   L29
    LINENUMBER 339 L29
    ALOAD 9
    GETSTATIC codechicken/nei/guihook/GuiContainerManager.stackTraces : Ljava/util/HashSet;
    ALOAD 2
    INVOKESTATIC codechicken/nei/NEIClientUtils.reportErrorBuffered (Ljava/lang/Throwable;Ljava/util/Set;Lnet/minecraft/item/ItemStack;)V
   L30
    LINENUMBER 341 L30
    INVOKESTATIC codechicken/nei/guihook/GuiContainerManager.restoreMatrixStack ()V
   L31
    LINENUMBER 342 L31
    GETSTATIC net/minecraft/client/renderer/Tessellator.instance : Lnet/minecraft/client/renderer/Tessellator;
    GETFIELD net/minecraft/client/renderer/Tessellator.isDrawing : Z
    IFEQ L32
    GETSTATIC net/minecraft/client/renderer/Tessellator.instance : Lnet/minecraft/client/renderer/Tessellator;
    INVOKEVIRTUAL net/minecraft/client/renderer/Tessellator.draw ()I
    POP
   L32
    LINENUMBER 344 L32
   FRAME FULL [I I net/minecraft/item/ItemStack net/minecraft/client/gui/FontRenderer I java/lang/String I F F java/lang/Exception] []
    GETSTATIC codechicken/nei/guihook/GuiContainerManager.drawItems : Lnet/minecraft/client/renderer/entity/RenderItem;
    FLOAD 7
    PUTFIELD net/minecraft/client/renderer/entity/RenderItem.zLevel : F
   L33
    LINENUMBER 345 L33
    GETSTATIC codechicken/nei/guihook/GuiContainerManager.drawItems : Lnet/minecraft/client/renderer/entity/RenderItem;
    ALOAD 3
    GETSTATIC codechicken/lib/gui/GuiDraw.renderEngine : Lnet/minecraft/client/renderer/texture/TextureManager;
    NEW net/minecraft/item/ItemStack
    DUP
    GETSTATIC net/minecraft/init/Blocks.fire : Lnet/minecraft/block/BlockFire;
    INVOKESPECIAL net/minecraft/item/ItemStack.<init> (Lnet/minecraft/block/Block;)V
    ILOAD 0
    ILOAD 1
    INVOKEVIRTUAL net/minecraft/client/renderer/entity/RenderItem.renderItemIntoGUI (Lnet/minecraft/client/gui/FontRenderer;Lnet/minecraft/client/renderer/texture/TextureManager;Lnet/minecraft/item/ItemStack;II)V
   L34
    LINENUMBER 346 L34
    GETSTATIC codechicken/nei/guihook/GuiContainerManager.renderingErrorItems : Lcodechicken/nei/ItemStackSet;
    ALOAD 2
    INVOKEVIRTUAL codechicken/nei/ItemStackSet.add (Lnet/minecraft/item/ItemStack;)V
   L28
    LINENUMBER 348 L28
   FRAME FULL [I I net/minecraft/item/ItemStack net/minecraft/client/gui/FontRenderer I java/lang/String I F F] []
    GOTO L35
   L7
    LINENUMBER 349 L7
   FRAME FULL [I I net/minecraft/item/ItemStack net/minecraft/client/gui/FontRenderer I java/lang/String I F] []
    GETSTATIC codechicken/nei/guihook/GuiContainerManager.drawItems : Lnet/minecraft/client/renderer/entity/RenderItem;
    ALOAD 3
    GETSTATIC codechicken/lib/gui/GuiDraw.renderEngine : Lnet/minecraft/client/renderer/texture/TextureManager;
    NEW net/minecraft/item/ItemStack
    DUP
    GETSTATIC net/minecraft/init/Blocks.fire : Lnet/minecraft/block/BlockFire;
    INVOKESPECIAL net/minecraft/item/ItemStack.<init> (Lnet/minecraft/block/Block;)V
    ILOAD 0
    ILOAD 1
    INVOKEVIRTUAL net/minecraft/client/renderer/entity/RenderItem.renderItemIntoGUI (Lnet/minecraft/client/gui/FontRenderer;Lnet/minecraft/client/renderer/texture/TextureManager;Lnet/minecraft/item/ItemStack;II)V
   L35
    LINENUMBER 352 L35
   FRAME FULL [I I net/minecraft/item/ItemStack net/minecraft/client/gui/FontRenderer I java/lang/String I F] []
    ILOAD 6
    IFEQ L36
   L37
    LINENUMBER 353 L37
    LDC 32826
    INVOKESTATIC org/lwjgl/opengl/GL11.glEnable (I)V
    GOTO L38
   L36
    LINENUMBER 355 L36
   FRAME FULL [I I net/minecraft/item/ItemStack net/minecraft/client/gui/FontRenderer I java/lang/String I F] []
    LDC 32826
    INVOKESTATIC org/lwjgl/opengl/GL11.glDisable (I)V
   L38
    LINENUMBER 358 L38
   FRAME FULL [I I net/minecraft/item/ItemStack net/minecraft/client/gui/FontRenderer I java/lang/String I F] []
    INVOKESTATIC codechicken/nei/guihook/GuiContainerManager.enable2DRender ()V
   L39
    LINENUMBER 359 L39
    GETSTATIC codechicken/nei/guihook/GuiContainerManager.drawItems : Lnet/minecraft/client/renderer/entity/RenderItem;
    FLOAD 7
    LDC 100.0
    FSUB
    PUTFIELD net/minecraft/client/renderer/entity/RenderItem.zLevel : F
   L40
    LINENUMBER 360 L40
    RETURN
   L41
    LOCALVARIABLE e Ljava/lang/Exception; L29 L28 9
    LOCALVARIABLE scale F L0 L28 8
    LOCALVARIABLE i I L3 L41 0
    LOCALVARIABLE j I L3 L41 1
    LOCALVARIABLE itemstack Lnet/minecraft/item/ItemStack; L3 L41 2
    LOCALVARIABLE fontRenderer Lnet/minecraft/client/gui/FontRenderer; L3 L41 3
    LOCALVARIABLE smallAmount Z L3 L41 4
    LOCALVARIABLE stackSize Ljava/lang/String; L3 L41 5
    LOCALVARIABLE glRescale Z L5 L41 6
    LOCALVARIABLE zLevel F L6 L41 7
    MAXSTACK = 7
    MAXLOCALS = 10

  // access flags 0xC
  protected static drawBigStackSize(IILjava/lang/String;F)V
   L0
    LINENUMBER 364 L0
    FCONST_1
    FLOAD 3
    FDIV
    FSTORE 4
   L1
    LINENUMBER 366 L1
    INVOKESTATIC codechicken/nei/guihook/GuiContainerManager.enable2DRender ()V
   L2
    LINENUMBER 367 L2
    FLOAD 3
    F2D
    FLOAD 3
    F2D
    FLOAD 3
    F2D
    INVOKESTATIC org/lwjgl/opengl/GL11.glScaled (DDD)V
   L3
    LINENUMBER 369 L3
    ILOAD 0
    I2F
    LDC 16.0
    FADD
    GETSTATIC codechicken/lib/gui/GuiDraw.fontRenderer : Lnet/minecraft/client/gui/FontRenderer;
    ALOAD 2
    INVOKEVIRTUAL net/minecraft/client/gui/FontRenderer.getStringWidth (Ljava/lang/String;)I
    I2F
    FLOAD 3
    FMUL
    FSUB
    FLOAD 4
    FMUL
    F2I
    ISTORE 5
   L4
    LINENUMBER 371 L4
    ILOAD 1
    I2F
    LDC 16.0
    FADD
    LDC 7.0
    FLOAD 3
    FMUL
    FSUB
    FLOAD 4
    FMUL
    F2I
    ISTORE 6
   L5
    LINENUMBER 372 L5
    GETSTATIC codechicken/lib/gui/GuiDraw.fontRenderer : Lnet/minecraft/client/gui/FontRenderer;
    ALOAD 2
    ILOAD 5
    ILOAD 6
    LDC 16777215
    INVOKEVIRTUAL net/minecraft/client/gui/FontRenderer.drawStringWithShadow (Ljava/lang/String;III)I
    POP
   L6
    LINENUMBER 374 L6
    FLOAD 4
    F2D
    FLOAD 4
    F2D
    FLOAD 4
    F2D
    INVOKESTATIC org/lwjgl/opengl/GL11.glScaled (DDD)V
   L7
    LINENUMBER 375 L7
    INVOKESTATIC codechicken/nei/guihook/GuiContainerManager.enable3DRender ()V
   L8
    LINENUMBER 376 L8
    RETURN
   L9
    LOCALVARIABLE offsetX I L0 L9 0
    LOCALVARIABLE offsetY I L0 L9 1
    LOCALVARIABLE stackSize Ljava/lang/String; L0 L9 2
    LOCALVARIABLE scale F L0 L9 3
    LOCALVARIABLE inverseScaleFactor F L1 L9 4
    LOCALVARIABLE X I L4 L9 5
    LOCALVARIABLE Y I L5 L9 6
    MAXSTACK = 6
    MAXLOCALS = 7

  // access flags 0x9
  public static registerReloadResourceListener()V
   L0
    LINENUMBER 379 L0
    INVOKESTATIC net/minecraft/client/Minecraft.getMinecraft ()Lnet/minecraft/client/Minecraft;
    INVOKEVIRTUAL net/minecraft/client/Minecraft.getResourceManager ()Lnet/minecraft/client/resources/IResourceManager;
    INSTANCEOF net/minecraft/client/resources/SimpleReloadableResourceManager
    IFEQ L1
   L2
    LINENUMBER 380 L2
    INVOKESTATIC net/minecraft/client/Minecraft.getMinecraft ()Lnet/minecraft/client/Minecraft;
   L3
    LINENUMBER 381 L3
    INVOKEVIRTUAL net/minecraft/client/Minecraft.getResourceManager ()Lnet/minecraft/client/resources/IResourceManager;
    CHECKCAST net/minecraft/client/resources/SimpleReloadableResourceManager
    ASTORE 0
   L4
    LINENUMBER 382 L4
    ALOAD 0
    NEW codechicken/nei/guihook/GuiContainerManager$ResourcePackReloaded
    DUP
    ACONST_NULL
    INVOKESPECIAL codechicken/nei/guihook/GuiContainerManager$ResourcePackReloaded.<init> (Lcodechicken/nei/guihook/GuiContainerManager$1;)V
    INVOKEVIRTUAL net/minecraft/client/resources/SimpleReloadableResourceManager.registerReloadListener (Lnet/minecraft/client/resources/IResourceManagerReloadListener;)V
   L1
    LINENUMBER 384 L1
   FRAME FULL [] []
    RETURN
    LOCALVARIABLE manager Lnet/minecraft/client/resources/SimpleReloadableResourceManager; L4 L1 0
    MAXSTACK = 4
    MAXLOCALS = 1

  // access flags 0x9
  public static enableMatrixStackLogging()V
   L0
    LINENUMBER 387 L0
    SIPUSH 2979
    INVOKESTATIC org/lwjgl/opengl/GL11.glGetInteger (I)I
    PUTSTATIC codechicken/nei/guihook/GuiContainerManager.modelviewDepth : I
   L1
    LINENUMBER 388 L1
    RETURN
    MAXSTACK = 1
    MAXLOCALS = 0

  // access flags 0x9
  public static disableMatrixStackLogging()V
   L0
    LINENUMBER 391 L0
    ICONST_M1
    PUTSTATIC codechicken/nei/guihook/GuiContainerManager.modelviewDepth : I
   L1
    LINENUMBER 392 L1
    RETURN
    MAXSTACK = 1
    MAXLOCALS = 0

  // access flags 0x9
  public static checkMatrixStack()Z
   L0
    LINENUMBER 395 L0
    GETSTATIC codechicken/nei/guihook/GuiContainerManager.modelviewDepth : I
    IFLT L1
    SIPUSH 2979
    INVOKESTATIC org/lwjgl/opengl/GL11.glGetInteger (I)I
    GETSTATIC codechicken/nei/guihook/GuiContainerManager.modelviewDepth : I
    IF_ICMPNE L2
   L1
   FRAME FULL [] []
    ICONST_1
    GOTO L3
   L2
   FRAME FULL [] []
    ICONST_0
   L3
   FRAME FULL [] [I]
    IRETURN
    MAXSTACK = 2
    MAXLOCALS = 0

  // access flags 0x9
  public static restoreMatrixStack()V
   L0
    LINENUMBER 399 L0
    GETSTATIC codechicken/nei/guihook/GuiContainerManager.modelviewDepth : I
    IFLT L1
   L2
    LINENUMBER 400 L2
    SIPUSH 2979
    INVOKESTATIC org/lwjgl/opengl/GL11.glGetInteger (I)I
    ISTORE 0
   L3
   FRAME FULL [I] []
    ILOAD 0
    GETSTATIC codechicken/nei/guihook/GuiContainerManager.modelviewDepth : I
    IF_ICMPLE L1
    INVOKESTATIC org/lwjgl/opengl/GL11.glPopMatrix ()V
    IINC 0 -1
    GOTO L3
   L1
    LINENUMBER 401 L1
   FRAME FULL [] []
    RETURN
    LOCALVARIABLE i I L3 L1 0
    MAXSTACK = 2
    MAXLOCALS = 1

  // access flags 0x9
  public static setColouredItemRender(Z)V
   L0
    LINENUMBER 404 L0
    GETSTATIC codechicken/nei/guihook/GuiContainerManager.drawItems : Lnet/minecraft/client/renderer/entity/RenderItem;
    ILOAD 0
    IFNE L1
    ICONST_1
    GOTO L2
   L1
   FRAME FULL [I] [net/minecraft/client/renderer/entity/RenderItem]
    ICONST_0
   L2
   FRAME FULL [I] [net/minecraft/client/renderer/entity/RenderItem I]
    PUTFIELD net/minecraft/client/renderer/entity/RenderItem.renderWithColor : Z
   L3
    LINENUMBER 405 L3
    RETURN
   L4
    LOCALVARIABLE enable Z L0 L4 0
    MAXSTACK = 2
    MAXLOCALS = 1

  // access flags 0x9
  public static enable3DRender()V
   L0
    LINENUMBER 408 L0
    SIPUSH 2896
    INVOKESTATIC org/lwjgl/opengl/GL11.glEnable (I)V
   L1
    LINENUMBER 409 L1
    SIPUSH 2929
    INVOKESTATIC org/lwjgl/opengl/GL11.glEnable (I)V
   L2
    LINENUMBER 410 L2
    RETURN
    MAXSTACK = 1
    MAXLOCALS = 0

  // access flags 0x9
  public static enable2DRender()V
   L0
    LINENUMBER 413 L0
    SIPUSH 2896
    INVOKESTATIC org/lwjgl/opengl/GL11.glDisable (I)V
   L1
    LINENUMBER 414 L1
    SIPUSH 2929
    INVOKESTATIC org/lwjgl/opengl/GL11.glDisable (I)V
   L2
    LINENUMBER 415 L2
    RETURN
    MAXSTACK = 1
    MAXLOCALS = 0

  // access flags 0x1
  public <init>(Lnet/minecraft/client/gui/inventory/GuiContainer;)V
   L0
    LINENUMBER 420 L0
    ALOAD 0
    INVOKESPECIAL java/lang/Object.<init> ()V
   L1
    LINENUMBER 417 L1
    ALOAD 0
    ICONST_0
    PUTFIELD codechicken/nei/guihook/GuiContainerManager.clickHandled : I
   L2
    LINENUMBER 421 L2
    ALOAD 0
    ALOAD 1
    PUTFIELD codechicken/nei/guihook/GuiContainerManager.window : Lnet/minecraft/client/gui/inventory/GuiContainer;
   L3
    LINENUMBER 422 L3
    ALOAD 1
    INSTANCEOF codechicken/nei/guihook/IContainerTooltipHandler
    IFEQ L4
   L5
    LINENUMBER 423 L5
    ALOAD 0
    NEW java/util/LinkedList
    DUP
    INVOKESPECIAL java/util/LinkedList.<init> ()V
    INVOKESTATIC java/util/Collections.synchronizedList (Ljava/util/List;)Ljava/util/List;
    PUTFIELD codechicken/nei/guihook/GuiContainerManager.instanceTooltipHandlers : Ljava/util/List;
   L6
    LINENUMBER 424 L6
    ALOAD 0
    GETFIELD codechicken/nei/guihook/GuiContainerManager.instanceTooltipHandlers : Ljava/util/List;
    ALOAD 1
    CHECKCAST codechicken/nei/guihook/IContainerTooltipHandler
    INVOKEINTERFACE java/util/List.add (Ljava/lang/Object;)Z
    POP
   L7
    LINENUMBER 425 L7
    ALOAD 0
    GETFIELD codechicken/nei/guihook/GuiContainerManager.instanceTooltipHandlers : Ljava/util/List;
    GETSTATIC codechicken/nei/guihook/GuiContainerManager.tooltipHandlers : Ljava/util/LinkedList;
    INVOKEINTERFACE java/util/List.addAll (Ljava/util/Collection;)Z
    POP
    GOTO L8
   L4
    LINENUMBER 426 L4
   FRAME FULL [codechicken/nei/guihook/GuiContainerManager net/minecraft/client/gui/inventory/GuiContainer] []
    ALOAD 0
    GETSTATIC codechicken/nei/guihook/GuiContainerManager.tooltipHandlers : Ljava/util/LinkedList;
    PUTFIELD codechicken/nei/guihook/GuiContainerManager.instanceTooltipHandlers : Ljava/util/List;
   L8
    LINENUMBER 427 L8
   FRAME FULL [codechicken/nei/guihook/GuiContainerManager net/minecraft/client/gui/inventory/GuiContainer] []
    RETURN
   L9
    LOCALVARIABLE this Lcodechicken/nei/guihook/GuiContainerManager; L0 L9 0
    LOCALVARIABLE screen Lnet/minecraft/client/gui/inventory/GuiContainer; L0 L9 1
    MAXSTACK = 3
    MAXLOCALS = 2

  // access flags 0x9
  public static getStackMouseOver(Lnet/minecraft/client/gui/inventory/GuiContainer;)Lnet/minecraft/item/ItemStack;
   L0
    LINENUMBER 430 L0
    INVOKESTATIC codechicken/lib/gui/GuiDraw.getMousePosition ()Ljava/awt/Point;
    ASTORE 1
   L1
    LINENUMBER 432 L1
    GETSTATIC codechicken/nei/guihook/GuiContainerManager.objectHandlers : Ljava/util/LinkedList;
    INVOKEVIRTUAL java/util/LinkedList.iterator ()Ljava/util/Iterator;
    ASTORE 2
   L2
   FRAME FULL [net/minecraft/client/gui/inventory/GuiContainer java/awt/Point java/util/Iterator] []
    ALOAD 2
    INVOKEINTERFACE java/util/Iterator.hasNext ()Z
    IFEQ L3
    ALOAD 2
    INVOKEINTERFACE java/util/Iterator.next ()Ljava/lang/Object;
    CHECKCAST codechicken/nei/guihook/IContainerObjectHandler
    ASTORE 3
   L4
    LINENUMBER 433 L4
    ALOAD 3
    ALOAD 0
    ALOAD 1
    GETFIELD java/awt/Point.x : I
    ALOAD 1
    GETFIELD java/awt/Point.y : I
    INVOKEINTERFACE codechicken/nei/guihook/IContainerObjectHandler.getStackUnderMouse (Lnet/minecraft/client/gui/inventory/GuiContainer;II)Lnet/minecraft/item/ItemStack;
    ASTORE 4
   L5
    LINENUMBER 434 L5
    ALOAD 4
    IFNULL L6
    ALOAD 4
    ARETURN
   L6
    LINENUMBER 435 L6
   FRAME FULL [net/minecraft/client/gui/inventory/GuiContainer java/awt/Point java/util/Iterator codechicken/nei/guihook/IContainerObjectHandler net/minecraft/item/ItemStack] []
    GOTO L2
   L3
    LINENUMBER 437 L3
   FRAME FULL [net/minecraft/client/gui/inventory/GuiContainer java/awt/Point java/util/Iterator] []
    ALOAD 0
    INVOKESTATIC codechicken/nei/guihook/GuiContainerManager.getSlotMouseOver (Lnet/minecraft/client/gui/inventory/GuiContainer;)Lnet/minecraft/inventory/Slot;
    ASTORE 2
   L7
    LINENUMBER 438 L7
    ALOAD 2
    IFNULL L8
    ALOAD 2
    INVOKEVIRTUAL net/minecraft/inventory/Slot.getStack ()Lnet/minecraft/item/ItemStack;
    ARETURN
   L8
    LINENUMBER 440 L8
   FRAME FULL [net/minecraft/client/gui/inventory/GuiContainer java/awt/Point net/minecraft/inventory/Slot] []
    ACONST_NULL
    ARETURN
   L9
    LOCALVARIABLE item Lnet/minecraft/item/ItemStack; L5 L6 4
    LOCALVARIABLE objectHandler Lcodechicken/nei/guihook/IContainerObjectHandler; L4 L6 3
    LOCALVARIABLE window Lnet/minecraft/client/gui/inventory/GuiContainer; L0 L9 0
    LOCALVARIABLE mousePos Ljava/awt/Point; L1 L9 1
    LOCALVARIABLE slot Lnet/minecraft/inventory/Slot; L7 L9 2
    MAXSTACK = 4
    MAXLOCALS = 5

  // access flags 0x9
  public static getSlotMouseOver(Lnet/minecraft/client/gui/inventory/GuiContainer;)Lnet/minecraft/inventory/Slot;
   L0
    LINENUMBER 444 L0
    INVOKESTATIC codechicken/lib/gui/GuiDraw.getMousePosition ()Ljava/awt/Point;
    ASTORE 1
   L1
    LINENUMBER 445 L1
    ALOAD 0
    INVOKESTATIC codechicken/nei/guihook/GuiContainerManager.getManager (Lnet/minecraft/client/gui/inventory/GuiContainer;)Lcodechicken/nei/guihook/GuiContainerManager;
    ALOAD 1
    GETFIELD java/awt/Point.x : I
    ALOAD 1
    GETFIELD java/awt/Point.y : I
    INVOKEVIRTUAL codechicken/nei/guihook/GuiContainerManager.objectUnderMouse (II)Z
    IFEQ L2
    ACONST_NULL
    ARETURN
   L2
    LINENUMBER 447 L2
   FRAME FULL [net/minecraft/client/gui/inventory/GuiContainer java/awt/Point] []
    ALOAD 0
    ALOAD 1
    GETFIELD java/awt/Point.x : I
    ALOAD 1
    GETFIELD java/awt/Point.y : I
    INVOKEVIRTUAL net/minecraft/client/gui/inventory/GuiContainer.getSlotAtPosition (II)Lnet/minecraft/inventory/Slot;
    ARETURN
   L3
    LOCALVARIABLE window Lnet/minecraft/client/gui/inventory/GuiContainer; L0 L3 0
    LOCALVARIABLE mousePos Ljava/awt/Point; L1 L3 1
    MAXSTACK = 3
    MAXLOCALS = 2

  // access flags 0x1
  public load()V
   L0
    LINENUMBER 451 L0
    ALOAD 0
    ICONST_0
    PUTFIELD codechicken/nei/guihook/GuiContainerManager.clickHandled : I
   L1
    LINENUMBER 452 L1
    GETSTATIC codechicken/nei/guihook/GuiContainerManager.objectHandlers : Ljava/util/LinkedList;
    INVOKEVIRTUAL java/util/LinkedList.iterator ()Ljava/util/Iterator;
    ASTORE 1
   L2
   FRAME FULL [codechicken/nei/guihook/GuiContainerManager java/util/Iterator] []
    ALOAD 1
    INVOKEINTERFACE java/util/Iterator.hasNext ()Z
    IFEQ L3
    ALOAD 1
    INVOKEINTERFACE java/util/Iterator.next ()Ljava/lang/Object;
    CHECKCAST codechicken/nei/guihook/IContainerObjectHandler
    ASTORE 2
   L4
    ALOAD 2
    ALOAD 0
    GETFIELD codechicken/nei/guihook/GuiContainerManager.window : Lnet/minecraft/client/gui/inventory/GuiContainer;
    INVOKEINTERFACE codechicken/nei/guihook/IContainerObjectHandler.load (Lnet/minecraft/client/gui/inventory/GuiContainer;)V
   L5
    GOTO L2
   L3
    LINENUMBER 453 L3
   FRAME FULL [codechicken/nei/guihook/GuiContainerManager java/util/Iterator] []
    RETURN
   L6
    LOCALVARIABLE objectHandler Lcodechicken/nei/guihook/IContainerObjectHandler; L4 L5 2
    LOCALVARIABLE this Lcodechicken/nei/guihook/GuiContainerManager; L0 L6 0
    MAXSTACK = 2
    MAXLOCALS = 3

  // access flags 0x1
  public updateScreen()V
   L0
    LINENUMBER 459 L0
    GETSTATIC codechicken/nei/guihook/GuiContainerManager.objectHandlers : Ljava/util/LinkedList;
    INVOKEVIRTUAL java/util/LinkedList.iterator ()Ljava/util/Iterator;
    ASTORE 1
   L1
   FRAME FULL [codechicken/nei/guihook/GuiContainerManager java/util/Iterator] []
    ALOAD 1
    INVOKEINTERFACE java/util/Iterator.hasNext ()Z
    IFEQ L2
    ALOAD 1
    INVOKEINTERFACE java/util/Iterator.next ()Ljava/lang/Object;
    CHECKCAST codechicken/nei/guihook/IContainerObjectHandler
    ASTORE 2
   L3
    ALOAD 2
    ALOAD 0
    GETFIELD codechicken/nei/guihook/GuiContainerManager.window : Lnet/minecraft/client/gui/inventory/GuiContainer;
    INVOKEINTERFACE codechicken/nei/guihook/IContainerObjectHandler.guiTick (Lnet/minecraft/client/gui/inventory/GuiContainer;)V
   L4
    GOTO L1
   L2
    LINENUMBER 460 L2
   FRAME FULL [codechicken/nei/guihook/GuiContainerManager java/util/Iterator] []
    RETURN
   L5
    LOCALVARIABLE objectHandler Lcodechicken/nei/guihook/IContainerObjectHandler; L3 L4 2
    LOCALVARIABLE this Lcodechicken/nei/guihook/GuiContainerManager; L0 L5 0
    MAXSTACK = 2
    MAXLOCALS = 3

  // access flags 0x1
  public lastKeyTyped(IC)Z
   L0
    LINENUMBER 466 L0
    ILOAD 1
    ICONST_1
    IF_ICMPNE L1
    ICONST_0
    IRETURN
   L1
    LINENUMBER 468 L1
   FRAME FULL [codechicken/nei/guihook/GuiContainerManager I I] []
    GETSTATIC codechicken/nei/guihook/GuiContainerManager.inputHandlers : Ljava/util/LinkedList;
    INVOKEVIRTUAL java/util/LinkedList.iterator ()Ljava/util/Iterator;
    ASTORE 3
   L2
   FRAME FULL [codechicken/nei/guihook/GuiContainerManager I I java/util/Iterator] []
    ALOAD 3
    INVOKEINTERFACE java/util/Iterator.hasNext ()Z
    IFEQ L3
    ALOAD 3
    INVOKEINTERFACE java/util/Iterator.next ()Ljava/lang/Object;
    CHECKCAST codechicken/nei/guihook/IContainerInputHandler
    ASTORE 4
   L4
    LINENUMBER 469 L4
    ALOAD 4
    ALOAD 0
    GETFIELD codechicken/nei/guihook/GuiContainerManager.window : Lnet/minecraft/client/gui/inventory/GuiContainer;
    ILOAD 2
    ILOAD 1
    INVOKEINTERFACE codechicken/nei/guihook/IContainerInputHandler.lastKeyTyped (Lnet/minecraft/client/gui/inventory/GuiContainer;CI)Z
    IFEQ L5
    ICONST_1
    IRETURN
   L5
   FRAME FULL [codechicken/nei/guihook/GuiContainerManager I I java/util/Iterator codechicken/nei/guihook/IContainerInputHandler] []
    GOTO L2
   L3
    LINENUMBER 471 L3
   FRAME FULL [codechicken/nei/guihook/GuiContainerManager I I java/util/Iterator] []
    ICONST_0
    IRETURN
   L6
    LOCALVARIABLE inputhander Lcodechicken/nei/guihook/IContainerInputHandler; L4 L5 4
    LOCALVARIABLE this Lcodechicken/nei/guihook/GuiContainerManager; L0 L6 0
    LOCALVARIABLE keyID I L0 L6 1
    LOCALVARIABLE keyChar C L0 L6 2
    MAXSTACK = 4
    MAXLOCALS = 5

  // access flags 0x1
  public firstKeyTyped(CI)Z
   L0
    LINENUMBER 475 L0
    GETSTATIC codechicken/nei/guihook/GuiContainerManager.inputHandlers : Ljava/util/LinkedList;
    INVOKEVIRTUAL java/util/LinkedList.iterator ()Ljava/util/Iterator;
    ASTORE 3
   L1
   FRAME FULL [codechicken/nei/guihook/GuiContainerManager I I java/util/Iterator] []
    ALOAD 3
    INVOKEINTERFACE java/util/Iterator.hasNext ()Z
    IFEQ L2
    ALOAD 3
    INVOKEINTERFACE java/util/Iterator.next ()Ljava/lang/Object;
    CHECKCAST codechicken/nei/guihook/IContainerInputHandler
    ASTORE 4
   L3
    ALOAD 4
    ALOAD 0
    GETFIELD codechicken/nei/guihook/GuiContainerManager.window : Lnet/minecraft/client/gui/inventory/GuiContainer;
    ILOAD 1
    ILOAD 2
    INVOKEINTERFACE codechicken/nei/guihook/IContainerInputHandler.onKeyTyped (Lnet/minecraft/client/gui/inventory/GuiContainer;CI)V
   L4
    GOTO L1
   L2
    LINENUMBER 477 L2
   FRAME FULL [codechicken/nei/guihook/GuiContainerManager I I java/util/Iterator] []
    GETSTATIC codechicken/nei/guihook/GuiContainerManager.inputHandlers : Ljava/util/LinkedList;
    INVOKEVIRTUAL java/util/LinkedList.iterator ()Ljava/util/Iterator;
    ASTORE 3
   L5
   FRAME FULL [codechicken/nei/guihook/GuiContainerManager I I java/util/Iterator] []
    ALOAD 3
    INVOKEINTERFACE java/util/Iterator.hasNext ()Z
    IFEQ L6
    ALOAD 3
    INVOKEINTERFACE java/util/Iterator.next ()Ljava/lang/Object;
    CHECKCAST codechicken/nei/guihook/IContainerInputHandler
    ASTORE 4
   L7
    LINENUMBER 478 L7
    ALOAD 4
    ALOAD 0
    GETFIELD codechicken/nei/guihook/GuiContainerManager.window : Lnet/minecraft/client/gui/inventory/GuiContainer;
    ILOAD 1
    ILOAD 2
    INVOKEINTERFACE codechicken/nei/guihook/IContainerInputHandler.keyTyped (Lnet/minecraft/client/gui/inventory/GuiContainer;CI)Z
    IFEQ L8
    ICONST_1
    IRETURN
   L8
   FRAME FULL [codechicken/nei/guihook/GuiContainerManager I I java/util/Iterator codechicken/nei/guihook/IContainerInputHandler] []
    GOTO L5
   L6
    LINENUMBER 480 L6
   FRAME FULL [codechicken/nei/guihook/GuiContainerManager I I java/util/Iterator] []
    ICONST_0
    IRETURN
   L9
    LOCALVARIABLE inputhander Lcodechicken/nei/guihook/IContainerInputHandler; L3 L4 4
    LOCALVARIABLE inputhander Lcodechicken/nei/guihook/IContainerInputHandler; L7 L8 4
    LOCALVARIABLE this Lcodechicken/nei/guihook/GuiContainerManager; L0 L9 0
    LOCALVARIABLE keyChar C L0 L9 1
    LOCALVARIABLE keyID I L0 L9 2
    MAXSTACK = 4
    MAXLOCALS = 5

  // access flags 0x1
  public mouseClicked(III)Z
   L0
    LINENUMBER 484 L0
    GETSTATIC codechicken/nei/guihook/GuiContainerManager.inputHandlers : Ljava/util/LinkedList;
    INVOKEVIRTUAL java/util/LinkedList.iterator ()Ljava/util/Iterator;
    ASTORE 4
   L1
   FRAME FULL [codechicken/nei/guihook/GuiContainerManager I I I java/util/Iterator] []
    ALOAD 4
    INVOKEINTERFACE java/util/Iterator.hasNext ()Z
    IFEQ L2
    ALOAD 4
    INVOKEINTERFACE java/util/Iterator.next ()Ljava/lang/Object;
    CHECKCAST codechicken/nei/guihook/IContainerInputHandler
    ASTORE 5
   L3
    LINENUMBER 485 L3
    ALOAD 5
    ALOAD 0
    GETFIELD codechicken/nei/guihook/GuiContainerManager.window : Lnet/minecraft/client/gui/inventory/GuiContainer;
    ILOAD 1
    ILOAD 2
    ILOAD 3
    INVOKEINTERFACE codechicken/nei/guihook/IContainerInputHandler.onMouseClicked (Lnet/minecraft/client/gui/inventory/GuiContainer;III)V
   L4
    GOTO L1
   L2
    LINENUMBER 487 L2
   FRAME FULL [codechicken/nei/guihook/GuiContainerManager I I I java/util/Iterator] []
    GETSTATIC codechicken/nei/guihook/GuiContainerManager.inputHandlers : Ljava/util/LinkedList;
    INVOKEVIRTUAL java/util/LinkedList.iterator ()Ljava/util/Iterator;
    ASTORE 4
   L5
   FRAME FULL [codechicken/nei/guihook/GuiContainerManager I I I java/util/Iterator] []
    ALOAD 4
    INVOKEINTERFACE java/util/Iterator.hasNext ()Z
    IFEQ L6
    ALOAD 4
    INVOKEINTERFACE java/util/Iterator.next ()Ljava/lang/Object;
    CHECKCAST codechicken/nei/guihook/IContainerInputHandler
    ASTORE 5
   L7
    LINENUMBER 488 L7
    ALOAD 5
    ALOAD 0
    GETFIELD codechicken/nei/guihook/GuiContainerManager.window : Lnet/minecraft/client/gui/inventory/GuiContainer;
    ILOAD 1
    ILOAD 2
    ILOAD 3
    INVOKEINTERFACE codechicken/nei/guihook/IContainerInputHandler.mouseClicked (Lnet/minecraft/client/gui/inventory/GuiContainer;III)Z
    IFEQ L8
   L9
    LINENUMBER 489 L9
    ALOAD 0
    DUP
    GETFIELD codechicken/nei/guihook/GuiContainerManager.clickHandled : I
    ICONST_1
    ILOAD 3
    ISHL
    IOR
    PUTFIELD codechicken/nei/guihook/GuiContainerManager.clickHandled : I
   L10
    LINENUMBER 490 L10
    ICONST_1
    IRETURN
   L8
    LINENUMBER 488 L8
   FRAME FULL [codechicken/nei/guihook/GuiContainerManager I I I java/util/Iterator codechicken/nei/guihook/IContainerInputHandler] []
    GOTO L5
   L6
    LINENUMBER 493 L6
   FRAME FULL [codechicken/nei/guihook/GuiContainerManager I I I java/util/Iterator] []
    ICONST_0
    IRETURN
   L11
    LOCALVARIABLE inputhander Lcodechicken/nei/guihook/IContainerInputHandler; L3 L4 5
    LOCALVARIABLE inputhander Lcodechicken/nei/guihook/IContainerInputHandler; L7 L8 5
    LOCALVARIABLE this Lcodechicken/nei/guihook/GuiContainerManager; L0 L11 0
    LOCALVARIABLE mousex I L0 L11 1
    LOCALVARIABLE mousey I L0 L11 2
    LOCALVARIABLE button I L0 L11 3
    MAXSTACK = 5
    MAXLOCALS = 6

  // access flags 0x1
  public mouseScrolled(I)V
   L0
    LINENUMBER 497 L0
    INVOKESTATIC codechicken/lib/gui/GuiDraw.getMousePosition ()Ljava/awt/Point;
    ASTORE 2
   L1
    LINENUMBER 499 L1
    GETSTATIC codechicken/nei/guihook/GuiContainerManager.inputHandlers : Ljava/util/LinkedList;
    INVOKEVIRTUAL java/util/LinkedList.iterator ()Ljava/util/Iterator;
    ASTORE 3
   L2
   FRAME FULL [codechicken/nei/guihook/GuiContainerManager I java/awt/Point java/util/Iterator] []
    ALOAD 3
    INVOKEINTERFACE java/util/Iterator.hasNext ()Z
    IFEQ L3
    ALOAD 3
    INVOKEINTERFACE java/util/Iterator.next ()Ljava/lang/Object;
    CHECKCAST codechicken/nei/guihook/IContainerInputHandler
    ASTORE 4
   L4
    LINENUMBER 500 L4
    ALOAD 4
    ALOAD 0
    GETFIELD codechicken/nei/guihook/GuiContainerManager.window : Lnet/minecraft/client/gui/inventory/GuiContainer;
    ALOAD 2
    GETFIELD java/awt/Point.x : I
    ALOAD 2
    GETFIELD java/awt/Point.y : I
    ILOAD 1
    INVOKEINTERFACE codechicken/nei/guihook/IContainerInputHandler.onMouseScrolled (Lnet/minecraft/client/gui/inventory/GuiContainer;III)V
   L5
    GOTO L2
   L3
    LINENUMBER 502 L3
   FRAME FULL [codechicken/nei/guihook/GuiContainerManager I java/awt/Point java/util/Iterator] []
    GETSTATIC codechicken/nei/guihook/GuiContainerManager.inputHandlers : Ljava/util/LinkedList;
    INVOKEVIRTUAL java/util/LinkedList.iterator ()Ljava/util/Iterator;
    ASTORE 3
   L6
   FRAME FULL [codechicken/nei/guihook/GuiContainerManager I java/awt/Point java/util/Iterator] []
    ALOAD 3
    INVOKEINTERFACE java/util/Iterator.hasNext ()Z
    IFEQ L7
    ALOAD 3
    INVOKEINTERFACE java/util/Iterator.next ()Ljava/lang/Object;
    CHECKCAST codechicken/nei/guihook/IContainerInputHandler
    ASTORE 4
   L8
    LINENUMBER 503 L8
    ALOAD 4
    ALOAD 0
    GETFIELD codechicken/nei/guihook/GuiContainerManager.window : Lnet/minecraft/client/gui/inventory/GuiContainer;
    ALOAD 2
    GETFIELD java/awt/Point.x : I
    ALOAD 2
    GETFIELD java/awt/Point.y : I
    ILOAD 1
    INVOKEINTERFACE codechicken/nei/guihook/IContainerInputHandler.mouseScrolled (Lnet/minecraft/client/gui/inventory/GuiContainer;III)Z
    IFEQ L9
    RETURN
   L9
   FRAME FULL [codechicken/nei/guihook/GuiContainerManager I java/awt/Point java/util/Iterator codechicken/nei/guihook/IContainerInputHandler] []
    GOTO L6
   L7
    LINENUMBER 505 L7
   FRAME FULL [codechicken/nei/guihook/GuiContainerManager I java/awt/Point java/util/Iterator] []
    ALOAD 0
    GETFIELD codechicken/nei/guihook/GuiContainerManager.window : Lnet/minecraft/client/gui/inventory/GuiContainer;
    INSTANCEOF codechicken/nei/guihook/IGuiHandleMouseWheel
    IFEQ L10
    ALOAD 0
    GETFIELD codechicken/nei/guihook/GuiContainerManager.window : Lnet/minecraft/client/gui/inventory/GuiContainer;
    CHECKCAST codechicken/nei/guihook/IGuiHandleMouseWheel
    ILOAD 1
    INVOKEINTERFACE codechicken/nei/guihook/IGuiHandleMouseWheel.mouseScrolled (I)V
   L10
    LINENUMBER 506 L10
   FRAME FULL [codechicken/nei/guihook/GuiContainerManager I java/awt/Point java/util/Iterator] []
    RETURN
   L11
    LOCALVARIABLE inputHandler Lcodechicken/nei/guihook/IContainerInputHandler; L4 L5 4
    LOCALVARIABLE inputHandler Lcodechicken/nei/guihook/IContainerInputHandler; L8 L9 4
    LOCALVARIABLE this Lcodechicken/nei/guihook/GuiContainerManager; L0 L11 0
    LOCALVARIABLE scrolled I L0 L11 1
    LOCALVARIABLE mousepos Ljava/awt/Point; L1 L11 2
    MAXSTACK = 5
    MAXLOCALS = 5

  // access flags 0x1
  public overrideMouseUp(III)Z
   L0
    LINENUMBER 512 L0
    ILOAD 3
    IFLT L1
    ALOAD 0
    GETFIELD codechicken/nei/guihook/GuiContainerManager.clickHandled : I
    ICONST_1
    ILOAD 3
    ISHL
    IAND
    IFEQ L1
   L2
    LINENUMBER 513 L2
    ALOAD 0
    DUP
    GETFIELD codechicken/nei/guihook/GuiContainerManager.clickHandled : I
    ICONST_1
    ILOAD 3
    ISHL
    ICONST_M1
    IXOR
    IAND
    PUTFIELD codechicken/nei/guihook/GuiContainerManager.clickHandled : I
   L3
    LINENUMBER 514 L3
    ALOAD 0
    ILOAD 1
    ILOAD 2
    ILOAD 3
    INVOKEVIRTUAL codechicken/nei/guihook/GuiContainerManager.mouseUp (III)V
   L4
    LINENUMBER 515 L4
    ICONST_1
    IRETURN
   L1
    LINENUMBER 517 L1
   FRAME FULL [codechicken/nei/guihook/GuiContainerManager I I I] []
    ICONST_0
    IRETURN
   L5
    LOCALVARIABLE this Lcodechicken/nei/guihook/GuiContainerManager; L0 L5 0
    LOCALVARIABLE mousex I L0 L5 1
    LOCALVARIABLE mousey I L0 L5 2
    LOCALVARIABLE button I L0 L5 3
    MAXSTACK = 4
    MAXLOCALS = 4

  // access flags 0x1
  public mouseUp(III)V
   L0
    LINENUMBER 521 L0
    GETSTATIC codechicken/nei/guihook/GuiContainerManager.inputHandlers : Ljava/util/LinkedList;
    INVOKEVIRTUAL java/util/LinkedList.iterator ()Ljava/util/Iterator;
    ASTORE 4
   L1
   FRAME FULL [codechicken/nei/guihook/GuiContainerManager I I I java/util/Iterator] []
    ALOAD 4
    INVOKEINTERFACE java/util/Iterator.hasNext ()Z
    IFEQ L2
    ALOAD 4
    INVOKEINTERFACE java/util/Iterator.next ()Ljava/lang/Object;
    CHECKCAST codechicken/nei/guihook/IContainerInputHandler
    ASTORE 5
   L3
    ALOAD 5
    ALOAD 0
    GETFIELD codechicken/nei/guihook/GuiContainerManager.window : Lnet/minecraft/client/gui/inventory/GuiContainer;
    ILOAD 1
    ILOAD 2
    ILOAD 3
    INVOKEINTERFACE codechicken/nei/guihook/IContainerInputHandler.onMouseUp (Lnet/minecraft/client/gui/inventory/GuiContainer;III)V
   L4
    GOTO L1
   L2
    LINENUMBER 522 L2
   FRAME FULL [codechicken/nei/guihook/GuiContainerManager I I I java/util/Iterator] []
    RETURN
   L5
    LOCALVARIABLE inputhander Lcodechicken/nei/guihook/IContainerInputHandler; L3 L4 5
    LOCALVARIABLE this Lcodechicken/nei/guihook/GuiContainerManager; L0 L5 0
    LOCALVARIABLE mousex I L0 L5 1
    LOCALVARIABLE mousey I L0 L5 2
    LOCALVARIABLE button I L0 L5 3
    MAXSTACK = 5
    MAXLOCALS = 6

  // access flags 0x1
  public mouseDragged(IIIJ)V
   L0
    LINENUMBER 528 L0
    GETSTATIC codechicken/nei/guihook/GuiContainerManager.inputHandlers : Ljava/util/LinkedList;
    INVOKEVIRTUAL java/util/LinkedList.iterator ()Ljava/util/Iterator;
    ASTORE 6
   L1
   FRAME FULL [codechicken/nei/guihook/GuiContainerManager I I I J java/util/Iterator] []
    ALOAD 6
    INVOKEINTERFACE java/util/Iterator.hasNext ()Z
    IFEQ L2
    ALOAD 6
    INVOKEINTERFACE java/util/Iterator.next ()Ljava/lang/Object;
    CHECKCAST codechicken/nei/guihook/IContainerInputHandler
    ASTORE 7
   L3
    LINENUMBER 529 L3
    ALOAD 7
    ALOAD 0
    GETFIELD codechicken/nei/guihook/GuiContainerManager.window : Lnet/minecraft/client/gui/inventory/GuiContainer;
    ILOAD 1
    ILOAD 2
    ILOAD 3
    LLOAD 4
    INVOKEINTERFACE codechicken/nei/guihook/IContainerInputHandler.onMouseDragged (Lnet/minecraft/client/gui/inventory/GuiContainer;IIIJ)V
   L4
    GOTO L1
   L2
    LINENUMBER 530 L2
   FRAME FULL [codechicken/nei/guihook/GuiContainerManager I I I J java/util/Iterator] []
    RETURN
   L5
    LOCALVARIABLE inputhander Lcodechicken/nei/guihook/IContainerInputHandler; L3 L4 7
    LOCALVARIABLE this Lcodechicken/nei/guihook/GuiContainerManager; L0 L5 0
    LOCALVARIABLE mousex I L0 L5 1
    LOCALVARIABLE mousey I L0 L5 2
    LOCALVARIABLE button I L0 L5 3
    LOCALVARIABLE heldTime J L0 L5 4
    MAXSTACK = 7
    MAXLOCALS = 8

  // access flags 0x1
  public preDraw()V
   L0
    LINENUMBER 536 L0
    GETSTATIC codechicken/nei/guihook/GuiContainerManager.drawHandlers : Ljava/util/LinkedList;
    INVOKEVIRTUAL java/util/LinkedList.iterator ()Ljava/util/Iterator;
    ASTORE 1
   L1
   FRAME FULL [codechicken/nei/guihook/GuiContainerManager java/util/Iterator] []
    ALOAD 1
    INVOKEINTERFACE java/util/Iterator.hasNext ()Z
    IFEQ L2
    ALOAD 1
    INVOKEINTERFACE java/util/Iterator.next ()Ljava/lang/Object;
    CHECKCAST codechicken/nei/guihook/IContainerDrawHandler
    ASTORE 2
   L3
    ALOAD 2
    ALOAD 0
    GETFIELD codechicken/nei/guihook/GuiContainerManager.window : Lnet/minecraft/client/gui/inventory/GuiContainer;
    INVOKEINTERFACE codechicken/nei/guihook/IContainerDrawHandler.onPreDraw (Lnet/minecraft/client/gui/inventory/GuiContainer;)V
   L4
    GOTO L1
   L2
    LINENUMBER 537 L2
   FRAME FULL [codechicken/nei/guihook/GuiContainerManager java/util/Iterator] []
    RETURN
   L5
    LOCALVARIABLE drawHandler Lcodechicken/nei/guihook/IContainerDrawHandler; L3 L4 2
    LOCALVARIABLE this Lcodechicken/nei/guihook/GuiContainerManager; L0 L5 0
    MAXSTACK = 2
    MAXLOCALS = 3

  // access flags 0x1
  public renderObjects(II)V
   L0
    LINENUMBER 540 L0
    ALOAD 0
    GETFIELD codechicken/nei/guihook/GuiContainerManager.window : Lnet/minecraft/client/gui/inventory/GuiContainer;
    GETFIELD net/minecraft/client/gui/inventory/GuiContainer.guiLeft : I
    INEG
    I2F
    ALOAD 0
    GETFIELD codechicken/nei/guihook/GuiContainerManager.window : Lnet/minecraft/client/gui/inventory/GuiContainer;
    GETFIELD net/minecraft/client/gui/inventory/GuiContainer.guiTop : I
    INEG
    I2F
    LDC 200.0
    INVOKESTATIC org/lwjgl/opengl/GL11.glTranslatef (FFF)V
   L1
    LINENUMBER 541 L1
    GETSTATIC codechicken/nei/guihook/GuiContainerManager.drawHandlers : Ljava/util/LinkedList;
    INVOKEVIRTUAL java/util/LinkedList.iterator ()Ljava/util/Iterator;
    ASTORE 3
   L2
   FRAME FULL [codechicken/nei/guihook/GuiContainerManager I I java/util/Iterator] []
    ALOAD 3
    INVOKEINTERFACE java/util/Iterator.hasNext ()Z
    IFEQ L3
    ALOAD 3
    INVOKEINTERFACE java/util/Iterator.next ()Ljava/lang/Object;
    CHECKCAST codechicken/nei/guihook/IContainerDrawHandler
    ASTORE 4
   L4
    ALOAD 4
    ALOAD 0
    GETFIELD codechicken/nei/guihook/GuiContainerManager.window : Lnet/minecraft/client/gui/inventory/GuiContainer;
    ILOAD 1
    ILOAD 2
    INVOKEINTERFACE codechicken/nei/guihook/IContainerDrawHandler.renderObjects (Lnet/minecraft/client/gui/inventory/GuiContainer;II)V
   L5
    GOTO L2
   L3
    LINENUMBER 543 L3
   FRAME FULL [codechicken/nei/guihook/GuiContainerManager I I java/util/Iterator] []
    GETSTATIC codechicken/nei/guihook/GuiContainerManager.drawHandlers : Ljava/util/LinkedList;
    INVOKEVIRTUAL java/util/LinkedList.iterator ()Ljava/util/Iterator;
    ASTORE 3
   L6
   FRAME FULL [codechicken/nei/guihook/GuiContainerManager I I java/util/Iterator] []
    ALOAD 3
    INVOKEINTERFACE java/util/Iterator.hasNext ()Z
    IFEQ L7
    ALOAD 3
    INVOKEINTERFACE java/util/Iterator.next ()Ljava/lang/Object;
    CHECKCAST codechicken/nei/guihook/IContainerDrawHandler
    ASTORE 4
   L8
    ALOAD 4
    ALOAD 0
    GETFIELD codechicken/nei/guihook/GuiContainerManager.window : Lnet/minecraft/client/gui/inventory/GuiContainer;
    ILOAD 1
    ILOAD 2
    INVOKEINTERFACE codechicken/nei/guihook/IContainerDrawHandler.postRenderObjects (Lnet/minecraft/client/gui/inventory/GuiContainer;II)V
   L9
    GOTO L6
   L7
    LINENUMBER 544 L7
   FRAME FULL [codechicken/nei/guihook/GuiContainerManager I I java/util/Iterator] []
    ALOAD 0
    GETFIELD codechicken/nei/guihook/GuiContainerManager.window : Lnet/minecraft/client/gui/inventory/GuiContainer;
    GETFIELD net/minecraft/client/gui/inventory/GuiContainer.guiLeft : I
    I2F
    ALOAD 0
    GETFIELD codechicken/nei/guihook/GuiContainerManager.window : Lnet/minecraft/client/gui/inventory/GuiContainer;
    GETFIELD net/minecraft/client/gui/inventory/GuiContainer.guiTop : I
    I2F
    LDC -200.0
    INVOKESTATIC org/lwjgl/opengl/GL11.glTranslatef (FFF)V
   L10
    LINENUMBER 545 L10
    RETURN
   L11
    LOCALVARIABLE drawHandler Lcodechicken/nei/guihook/IContainerDrawHandler; L4 L5 4
    LOCALVARIABLE drawHandler Lcodechicken/nei/guihook/IContainerDrawHandler; L8 L9 4
    LOCALVARIABLE this Lcodechicken/nei/guihook/GuiContainerManager; L0 L11 0
    LOCALVARIABLE mousex I L0 L11 1
    LOCALVARIABLE mousey I L0 L11 2
    MAXSTACK = 4
    MAXLOCALS = 5

  // access flags 0x1
  public renderToolTips(II)V
    TRYCATCHBLOCK L0 L1 L2 null
    TRYCATCHBLOCK L2 L3 L2 null
    TRYCATCHBLOCK L4 L5 L6 null
    TRYCATCHBLOCK L6 L7 L6 null
    TRYCATCHBLOCK L8 L9 L10 null
    TRYCATCHBLOCK L10 L11 L10 null
   L12
    LINENUMBER 548 L12
    NEW java/util/LinkedList
    DUP
    INVOKESPECIAL java/util/LinkedList.<init> ()V
    ASTORE 3
   L13
    LINENUMBER 549 L13
    NEW java/util/HashMap
    DUP
    INVOKESPECIAL java/util/HashMap.<init> ()V
    ASTORE 4
   L14
    LINENUMBER 550 L14
    GETSTATIC codechicken/lib/gui/GuiDraw.fontRenderer : Lnet/minecraft/client/gui/FontRenderer;
    ASTORE 5
   L15
    LINENUMBER 552 L15
    ALOAD 0
    GETFIELD codechicken/nei/guihook/GuiContainerManager.instanceTooltipHandlers : Ljava/util/List;
    DUP
    ASTORE 6
    MONITORENTER
   L0
    LINENUMBER 553 L0
    ALOAD 0
    GETFIELD codechicken/nei/guihook/GuiContainerManager.instanceTooltipHandlers : Ljava/util/List;
    INVOKEINTERFACE java/util/List.iterator ()Ljava/util/Iterator;
    ASTORE 7
   L16
   FRAME FULL [codechicken/nei/guihook/GuiContainerManager I I java/util/List java/util/HashMap net/minecraft/client/gui/FontRenderer java/util/List java/util/Iterator] []
    ALOAD 7
    INVOKEINTERFACE java/util/Iterator.hasNext ()Z
    IFEQ L17
    ALOAD 7
    INVOKEINTERFACE java/util/Iterator.next ()Ljava/lang/Object;
    CHECKCAST codechicken/nei/guihook/IContainerTooltipHandler
    ASTORE 8
   L18
    LINENUMBER 554 L18
    ALOAD 8
    ALOAD 0
    GETFIELD codechicken/nei/guihook/GuiContainerManager.window : Lnet/minecraft/client/gui/inventory/GuiContainer;
    ILOAD 1
    ILOAD 2
    ALOAD 3
    INVOKEINTERFACE codechicken/nei/guihook/IContainerTooltipHandler.handleTooltip (Lnet/minecraft/client/gui/inventory/GuiContainer;IILjava/util/List;)Ljava/util/List;
    ASTORE 3
   L19
    GOTO L16
   L17
    LINENUMBER 555 L17
   FRAME FULL [codechicken/nei/guihook/GuiContainerManager I I java/util/List java/util/HashMap net/minecraft/client/gui/FontRenderer java/util/List java/util/Iterator] []
    ALOAD 6
    MONITOREXIT
   L1
    GOTO L20
   L2
   FRAME FULL [codechicken/nei/guihook/GuiContainerManager I I java/util/List java/util/HashMap net/minecraft/client/gui/FontRenderer java/util/List] [java/lang/Throwable]
    ASTORE 9
    ALOAD 6
    MONITOREXIT
   L3
    ALOAD 9
    ATHROW
   L20
    LINENUMBER 557 L20
   FRAME FULL [codechicken/nei/guihook/GuiContainerManager I I java/util/List java/util/HashMap net/minecraft/client/gui/FontRenderer java/util/List java/util/Iterator] []
    ALOAD 3
    INVOKEINTERFACE java/util/List.isEmpty ()Z
    IFEQ L21
    ALOAD 0
    GETFIELD codechicken/nei/guihook/GuiContainerManager.window : Lnet/minecraft/client/gui/inventory/GuiContainer;
    INVOKESTATIC codechicken/nei/guihook/GuiContainerManager.shouldShowTooltip (Lnet/minecraft/client/gui/inventory/GuiContainer;)Z
    IFEQ L21
   L22
    LINENUMBER 558 L22
    ALOAD 0
    GETFIELD codechicken/nei/guihook/GuiContainerManager.window : Lnet/minecraft/client/gui/inventory/GuiContainer;
    INVOKESTATIC codechicken/nei/guihook/GuiContainerManager.getStackMouseOver (Lnet/minecraft/client/gui/inventory/GuiContainer;)Lnet/minecraft/item/ItemStack;
    ASTORE 6
   L23
    LINENUMBER 559 L23
    ALOAD 6
    INVOKESTATIC codechicken/nei/guihook/GuiContainerManager.getFontRenderer (Lnet/minecraft/item/ItemStack;)Lnet/minecraft/client/gui/FontRenderer;
    ASTORE 5
   L24
    LINENUMBER 560 L24
    ALOAD 6
    IFNULL L25
   L26
    LINENUMBER 561 L26
    ALOAD 6
    ALOAD 0
    GETFIELD codechicken/nei/guihook/GuiContainerManager.window : Lnet/minecraft/client/gui/inventory/GuiContainer;
    ICONST_1
    INVOKESTATIC codechicken/nei/guihook/GuiContainerManager.itemDisplayNameMultiline (Lnet/minecraft/item/ItemStack;Lnet/minecraft/client/gui/inventory/GuiContainer;Z)Ljava/util/List;
    ASTORE 3
   L27
    LINENUMBER 562 L27
    ALOAD 3
    ALOAD 6
    INVOKESTATIC codechicken/nei/guihook/GuiContainerManager.applyItemCountDetails (Ljava/util/List;Lnet/minecraft/item/ItemStack;)V
   L25
    LINENUMBER 565 L25
   FRAME FULL [codechicken/nei/guihook/GuiContainerManager I I java/util/List java/util/HashMap net/minecraft/client/gui/FontRenderer net/minecraft/item/ItemStack java/util/Iterator] []
    ALOAD 0
    GETFIELD codechicken/nei/guihook/GuiContainerManager.instanceTooltipHandlers : Ljava/util/List;
    DUP
    ASTORE 7
    MONITORENTER
   L4
    LINENUMBER 566 L4
    ALOAD 0
    GETFIELD codechicken/nei/guihook/GuiContainerManager.instanceTooltipHandlers : Ljava/util/List;
    INVOKEINTERFACE java/util/List.iterator ()Ljava/util/Iterator;
    ASTORE 8
   L28
   FRAME FULL [codechicken/nei/guihook/GuiContainerManager I I java/util/List java/util/HashMap net/minecraft/client/gui/FontRenderer net/minecraft/item/ItemStack java/util/List java/util/Iterator] []
    ALOAD 8
    INVOKEINTERFACE java/util/Iterator.hasNext ()Z
    IFEQ L29
    ALOAD 8
    INVOKEINTERFACE java/util/Iterator.next ()Ljava/lang/Object;
    CHECKCAST codechicken/nei/guihook/IContainerTooltipHandler
    ASTORE 9
   L30
    LINENUMBER 567 L30
    ALOAD 9
    ALOAD 0
    GETFIELD codechicken/nei/guihook/GuiContainerManager.window : Lnet/minecraft/client/gui/inventory/GuiContainer;
    ALOAD 6
    ILOAD 1
    ILOAD 2
    ALOAD 3
    INVOKEINTERFACE codechicken/nei/guihook/IContainerTooltipHandler.handleItemTooltip (Lnet/minecraft/client/gui/inventory/GuiContainer;Lnet/minecraft/item/ItemStack;IILjava/util/List;)Ljava/util/List;
    ASTORE 3
   L31
    GOTO L28
   L29
    LINENUMBER 568 L29
   FRAME FULL [codechicken/nei/guihook/GuiContainerManager I I java/util/List java/util/HashMap net/minecraft/client/gui/FontRenderer net/minecraft/item/ItemStack java/util/List java/util/Iterator] []
    ALOAD 7
    MONITOREXIT
   L5
    GOTO L21
   L6
   FRAME FULL [codechicken/nei/guihook/GuiContainerManager I I java/util/List java/util/HashMap net/minecraft/client/gui/FontRenderer net/minecraft/item/ItemStack java/util/List] [java/lang/Throwable]
    ASTORE 10
    ALOAD 7
    MONITOREXIT
   L7
    ALOAD 10
    ATHROW
   L21
    LINENUMBER 571 L21
   FRAME FULL [codechicken/nei/guihook/GuiContainerManager I I java/util/List java/util/HashMap net/minecraft/client/gui/FontRenderer java/lang/Object java/lang/Object] []
    ALOAD 3
    INVOKEINTERFACE java/util/List.isEmpty ()Z
    IFNE L32
    ALOAD 3
    ICONST_0
    NEW java/lang/StringBuilder
    DUP
    INVOKESPECIAL java/lang/StringBuilder.<init> ()V
    ALOAD 3
    ICONST_0
    INVOKEINTERFACE java/util/List.get (I)Ljava/lang/Object;
    CHECKCAST java/lang/String
    INVOKEVIRTUAL java/lang/StringBuilder.append (Ljava/lang/String;)Ljava/lang/StringBuilder;
    LDC "\u00a7h"
    INVOKEVIRTUAL java/lang/StringBuilder.append (Ljava/lang/String;)Ljava/lang/StringBuilder;
    INVOKEVIRTUAL java/lang/StringBuilder.toString ()Ljava/lang/String;
    INVOKEINTERFACE java/util/List.set (ILjava/lang/Object;)Ljava/lang/Object;
    POP
   L32
    LINENUMBER 573 L32
   FRAME FULL [codechicken/nei/guihook/GuiContainerManager I I java/util/List java/util/HashMap net/minecraft/client/gui/FontRenderer java/lang/Object java/lang/Object] []
    ALOAD 0
    GETFIELD codechicken/nei/guihook/GuiContainerManager.instanceTooltipHandlers : Ljava/util/List;
    DUP
    ASTORE 6
    MONITORENTER
   L8
    LINENUMBER 574 L8
    ALOAD 0
    GETFIELD codechicken/nei/guihook/GuiContainerManager.instanceTooltipHandlers : Ljava/util/List;
    INVOKEINTERFACE java/util/List.iterator ()Ljava/util/Iterator;
    ASTORE 7
   L33
   FRAME FULL [codechicken/nei/guihook/GuiContainerManager I I java/util/List java/util/Map net/minecraft/client/gui/FontRenderer java/util/List java/util/Iterator] []
    ALOAD 7
    INVOKEINTERFACE java/util/Iterator.hasNext ()Z
    IFEQ L34
    ALOAD 7
    INVOKEINTERFACE java/util/Iterator.next ()Ljava/lang/Object;
    CHECKCAST codechicken/nei/guihook/IContainerTooltipHandler
    ASTORE 8
   L35
    LINENUMBER 575 L35
    ALOAD 8
    ALOAD 0
    GETFIELD codechicken/nei/guihook/GuiContainerManager.window : Lnet/minecraft/client/gui/inventory/GuiContainer;
    ILOAD 1
    ILOAD 2
    ALOAD 4
    INVOKEINTERFACE codechicken/nei/guihook/IContainerTooltipHandler.handleHotkeys (Lnet/minecraft/client/gui/inventory/GuiContainer;IILjava/util/Map;)Ljava/util/Map;
    ASTORE 4
   L36
    LINENUMBER 576 L36
    GOTO L33
   L34
    LINENUMBER 577 L34
   FRAME FULL [codechicken/nei/guihook/GuiContainerManager I I java/util/List java/util/Map net/minecraft/client/gui/FontRenderer java/util/List java/util/Iterator] []
    ALOAD 6
    MONITOREXIT
   L9
    GOTO L37
   L10
   FRAME FULL [codechicken/nei/guihook/GuiContainerManager I I java/util/List java/util/Map net/minecraft/client/gui/FontRenderer java/util/List java/lang/Object] [java/lang/Throwable]
    ASTORE 11
    ALOAD 6
    MONITOREXIT
   L11
    ALOAD 11
    ATHROW
   L37
    LINENUMBER 579 L37
   FRAME FULL [codechicken/nei/guihook/GuiContainerManager I I java/util/List java/util/Map net/minecraft/client/gui/FontRenderer java/util/List java/util/Iterator] []
    ALOAD 4
    INVOKEINTERFACE java/util/Map.isEmpty ()Z
    IFNE L38
   L39
    LINENUMBER 580 L39
    NEW java/util/ArrayList
    DUP
    INVOKESPECIAL java/util/ArrayList.<init> ()V
    ASTORE 6
   L40
    LINENUMBER 582 L40
    INVOKESTATIC codechicken/nei/NEIClientUtils.altKey ()Z
    IFNE L41
   L42
    LINENUMBER 583 L42
    ALOAD 6
    NEW java/lang/StringBuilder
    DUP
    INVOKESPECIAL java/lang/StringBuilder.<init> ()V
    GETSTATIC net/minecraft/util/EnumChatFormatting.GRAY : Lnet/minecraft/util/EnumChatFormatting;
    INVOKEVIRTUAL java/lang/StringBuilder.append (Ljava/lang/Object;)Ljava/lang/StringBuilder;
    LDC "showHotkeys"
    ICONST_1
    ANEWARRAY java/lang/Object
    DUP
    ICONST_0
    NEW java/lang/StringBuilder
    DUP
    INVOKESPECIAL java/lang/StringBuilder.<init> ()V
    GETSTATIC net/minecraft/util/EnumChatFormatting.GOLD : Lnet/minecraft/util/EnumChatFormatting;
    INVOKEVIRTUAL java/lang/StringBuilder.append (Ljava/lang/Object;)Ljava/lang/StringBuilder;
    LDC "ALT"
    INVOKEVIRTUAL java/lang/StringBuilder.append (Ljava/lang/String;)Ljava/lang/StringBuilder;
    GETSTATIC net/minecraft/util/EnumChatFormatting.GRAY : Lnet/minecraft/util/EnumChatFormatting;
    INVOKEVIRTUAL java/lang/StringBuilder.append (Ljava/lang/Object;)Ljava/lang/StringBuilder;
    INVOKEVIRTUAL java/lang/StringBuilder.toString ()Ljava/lang/String;
    AASTORE
   L43
    LINENUMBER 585 L43
    INVOKESTATIC codechicken/nei/NEIClientUtils.translate (Ljava/lang/String;[Ljava/lang/Object;)Ljava/lang/String;
    INVOKEVIRTUAL java/lang/StringBuilder.append (Ljava/lang/String;)Ljava/lang/StringBuilder;
    INVOKEVIRTUAL java/lang/StringBuilder.toString ()Ljava/lang/String;
   L44
    LINENUMBER 583 L44
    INVOKEINTERFACE java/util/List.add (Ljava/lang/Object;)Z
    POP
    GOTO L45
   L41
    LINENUMBER 588 L41
   FRAME FULL [codechicken/nei/guihook/GuiContainerManager I I java/util/List java/util/Map net/minecraft/client/gui/FontRenderer java/util/ArrayList java/util/Iterator] []
    ALOAD 4
    INVOKEINTERFACE java/util/Map.entrySet ()Ljava/util/Set;
    INVOKEINTERFACE java/util/Set.iterator ()Ljava/util/Iterator;
    ASTORE 7
   L46
   FRAME FULL [codechicken/nei/guihook/GuiContainerManager I I java/util/List java/util/Map net/minecraft/client/gui/FontRenderer java/util/ArrayList java/util/Iterator] []
    ALOAD 7
    INVOKEINTERFACE java/util/Iterator.hasNext ()Z
    IFEQ L47
    ALOAD 7
    INVOKEINTERFACE java/util/Iterator.next ()Ljava/lang/Object;
    CHECKCAST java/util/Map$Entry
    ASTORE 8
   L48
    LINENUMBER 589 L48
    ALOAD 6
    ALOAD 0
    ALOAD 8
    INVOKEINTERFACE java/util/Map$Entry.getKey ()Ljava/lang/Object;
    CHECKCAST java/lang/String
    ALOAD 8
    INVOKEINTERFACE java/util/Map$Entry.getValue ()Ljava/lang/Object;
    CHECKCAST java/lang/String
    INVOKESPECIAL codechicken/nei/guihook/GuiContainerManager.getHotkeyTip (Ljava/lang/String;Ljava/lang/String;)Ljava/lang/String;
    INVOKEINTERFACE java/util/List.add (Ljava/lang/Object;)Z
    POP
   L49
    LINENUMBER 590 L49
    GOTO L46
   L47
    LINENUMBER 592 L47
   FRAME FULL [codechicken/nei/guihook/GuiContainerManager I I java/util/List java/util/Map net/minecraft/client/gui/FontRenderer java/util/ArrayList java/util/Iterator] []
    ALOAD 6
    INVOKEDYNAMIC compare()Ljava/util/Comparator; [
      // handle kind 0x6 : INVOKESTATIC
      java/lang/invoke/LambdaMetafactory.metafactory(Ljava/lang/invoke/MethodHandles$Lookup;Ljava/lang/String;Ljava/lang/invoke/MethodType;Ljava/lang/invoke/MethodType;Ljava/lang/invoke/MethodHandle;Ljava/lang/invoke/MethodType;)Ljava/lang/invoke/CallSite;
      // arguments:
      (Ljava/lang/Object;Ljava/lang/Object;)I, 
      // handle kind 0x6 : INVOKESTATIC
      codechicken/nei/guihook/GuiContainerManager.lambda$renderToolTips$0(Ljava/lang/String;Ljava/lang/String;)I, 
      (Ljava/lang/String;Ljava/lang/String;)I
    ]
    INVOKEINTERFACE java/util/List.sort (Ljava/util/Comparator;)V
   L50
    LINENUMBER 593 L50
    ALOAD 6
    ALOAD 6
   L51
    LINENUMBER 594 L51
    INVOKEINTERFACE java/util/List.size ()I
    ICONST_1
    ISUB
    NEW java/lang/StringBuilder
    DUP
    INVOKESPECIAL java/lang/StringBuilder.<init> ()V
    ALOAD 6
    ALOAD 6
   L52
    LINENUMBER 595 L52
    INVOKEINTERFACE java/util/List.size ()I
    ICONST_1
    ISUB
    INVOKEINTERFACE java/util/List.get (I)Ljava/lang/Object;
    CHECKCAST java/lang/String
    INVOKEVIRTUAL java/lang/StringBuilder.append (Ljava/lang/String;)Ljava/lang/StringBuilder;
    LDC "\u00a7h"
    INVOKEVIRTUAL java/lang/StringBuilder.append (Ljava/lang/String;)Ljava/lang/StringBuilder;
    INVOKEVIRTUAL java/lang/StringBuilder.toString ()Ljava/lang/String;
   L53
    LINENUMBER 593 L53
    INVOKEINTERFACE java/util/List.set (ILjava/lang/Object;)Ljava/lang/Object;
    POP
   L45
    LINENUMBER 598 L45
   FRAME FULL [codechicken/nei/guihook/GuiContainerManager I I java/util/List java/util/Map net/minecraft/client/gui/FontRenderer java/util/ArrayList java/util/Iterator] []
    ALOAD 3
    INVOKEINTERFACE java/util/List.isEmpty ()Z
    IFEQ L54
   L55
    LINENUMBER 599 L55
    ALOAD 3
    ALOAD 6
    INVOKEINTERFACE java/util/List.addAll (Ljava/util/Collection;)Z
    POP
    GOTO L38
   L54
    LINENUMBER 601 L54
   FRAME FULL [codechicken/nei/guihook/GuiContainerManager I I java/util/List java/util/Map net/minecraft/client/gui/FontRenderer java/util/ArrayList java/util/Iterator] []
    ALOAD 3
    ICONST_1
    ALOAD 6
    INVOKEINTERFACE java/util/List.addAll (ILjava/util/Collection;)Z
    POP
   L38
    LINENUMBER 605 L38
   FRAME FULL [codechicken/nei/guihook/GuiContainerManager I I java/util/List java/util/Map net/minecraft/client/gui/FontRenderer java/util/List java/util/Iterator] []
    ALOAD 5
    ILOAD 1
    BIPUSH 12
    IADD
    ILOAD 2
    BIPUSH 12
    ISUB
    ALOAD 3
    INVOKESTATIC codechicken/nei/guihook/GuiContainerManager.drawPagedTooltip (Lnet/minecraft/client/gui/FontRenderer;IILjava/util/List;)V
   L56
    LINENUMBER 607 L56
    GETSTATIC codechicken/nei/guihook/GuiContainerManager.drawHandlers : Ljava/util/LinkedList;
    INVOKEVIRTUAL java/util/LinkedList.iterator ()Ljava/util/Iterator;
    ASTORE 6
   L57
   FRAME FULL [codechicken/nei/guihook/GuiContainerManager I I java/util/List java/util/Map net/minecraft/client/gui/FontRenderer java/util/Iterator java/lang/Object] []
    ALOAD 6
    INVOKEINTERFACE java/util/Iterator.hasNext ()Z
    IFEQ L58
    ALOAD 6
    INVOKEINTERFACE java/util/Iterator.next ()Ljava/lang/Object;
    CHECKCAST codechicken/nei/guihook/IContainerDrawHandler
    ASTORE 7
   L59
    LINENUMBER 608 L59
    ALOAD 7
    ALOAD 0
    GETFIELD codechicken/nei/guihook/GuiContainerManager.window : Lnet/minecraft/client/gui/inventory/GuiContainer;
    ILOAD 1
    ILOAD 2
    ALOAD 3
    INVOKEINTERFACE codechicken/nei/guihook/IContainerDrawHandler.postRenderTooltips (Lnet/minecraft/client/gui/inventory/GuiContainer;IILjava/util/List;)V
   L60
    LINENUMBER 609 L60
    GOTO L57
   L58
    LINENUMBER 610 L58
   FRAME FULL [codechicken/nei/guihook/GuiContainerManager I I java/util/List java/util/Map net/minecraft/client/gui/FontRenderer java/util/Iterator java/lang/Object] []
    RETURN
   L61
    LOCALVARIABLE handler Lcodechicken/nei/guihook/IContainerTooltipHandler; L18 L19 8
    LOCALVARIABLE handler Lcodechicken/nei/guihook/IContainerTooltipHandler; L30 L31 9
    LOCALVARIABLE stack Lnet/minecraft/item/ItemStack; L23 L21 6
    LOCALVARIABLE handler Lcodechicken/nei/guihook/IContainerTooltipHandler; L35 L36 8
    LOCALVARIABLE entry Ljava/util/Map$Entry; L48 L49 8
    // signature Ljava/util/Map$Entry<Ljava/lang/String;Ljava/lang/String;>;
    // declaration: java.util.Map$Entry<java.lang.String, java.lang.String>
    LOCALVARIABLE hotkeystips Ljava/util/List; L40 L38 6
    // signature Ljava/util/List<Ljava/lang/String;>;
    // declaration: java.util.List<java.lang.String>
    LOCALVARIABLE drawHandler Lcodechicken/nei/guihook/IContainerDrawHandler; L59 L60 7
    LOCALVARIABLE this Lcodechicken/nei/guihook/GuiContainerManager; L12 L61 0
    LOCALVARIABLE mousex I L12 L61 1
    LOCALVARIABLE mousey I L12 L61 2
    LOCALVARIABLE tooltip Ljava/util/List; L13 L61 3
    // signature Ljava/util/List<Ljava/lang/String;>;
    // declaration: java.util.List<java.lang.String>
    LOCALVARIABLE hotkeys Ljava/util/Map; L14 L61 4
    // signature Ljava/util/Map<Ljava/lang/String;Ljava/lang/String;>;
    // declaration: java.util.Map<java.lang.String, java.lang.String>
    LOCALVARIABLE font Lnet/minecraft/client/gui/FontRenderer; L15 L61 5
    MAXSTACK = 8
    MAXLOCALS = 12

  // access flags 0x2
  private getHotkeyTip(Ljava/lang/String;Ljava/lang/String;)Ljava/lang/String;
   L0
    LINENUMBER 613 L0
    NEW java/lang/StringBuilder
    DUP
    INVOKESPECIAL java/lang/StringBuilder.<init> ()V
    GETSTATIC net/minecraft/util/EnumChatFormatting.GOLD : Lnet/minecraft/util/EnumChatFormatting;
    INVOKEVIRTUAL java/lang/StringBuilder.append (Ljava/lang/Object;)Ljava/lang/StringBuilder;
    ALOAD 1
    INVOKEVIRTUAL java/lang/StringBuilder.append (Ljava/lang/String;)Ljava/lang/StringBuilder;
    GETSTATIC net/minecraft/util/EnumChatFormatting.GRAY : Lnet/minecraft/util/EnumChatFormatting;
    INVOKEVIRTUAL java/lang/StringBuilder.append (Ljava/lang/Object;)Ljava/lang/StringBuilder;
    LDC " - "
    INVOKEVIRTUAL java/lang/StringBuilder.append (Ljava/lang/String;)Ljava/lang/StringBuilder;
    ALOAD 2
    INVOKEVIRTUAL java/lang/StringBuilder.append (Ljava/lang/String;)Ljava/lang/StringBuilder;
    GETSTATIC net/minecraft/util/EnumChatFormatting.RESET : Lnet/minecraft/util/EnumChatFormatting;
    INVOKEVIRTUAL java/lang/StringBuilder.append (Ljava/lang/Object;)Ljava/lang/StringBuilder;
    INVOKEVIRTUAL java/lang/StringBuilder.toString ()Ljava/lang/String;
    ARETURN
   L1
    LOCALVARIABLE this Lcodechicken/nei/guihook/GuiContainerManager; L0 L1 0
    LOCALVARIABLE key Ljava/lang/String; L0 L1 1
    LOCALVARIABLE message Ljava/lang/String; L0 L1 2
    MAXSTACK = 2
    MAXLOCALS = 3

  // access flags 0x9
  // signature (Lnet/minecraft/client/gui/FontRenderer;IILjava/util/List<Ljava/lang/String;>;)V
  // declaration: void drawPagedTooltip(net.minecraft.client.gui.FontRenderer, int, int, java.util.List<java.lang.String>)
  public static drawPagedTooltip(Lnet/minecraft/client/gui/FontRenderer;IILjava/util/List;)V
   L0
    LINENUMBER 619 L0
    ALOAD 3
    INVOKEINTERFACE java/util/List.isEmpty ()Z
    IFEQ L1
    RETURN
   L1
    LINENUMBER 620 L1
   FRAME FULL [net/minecraft/client/gui/FontRenderer I I java/util/List] []
    ALOAD 3
    INVOKESTATIC codechicken/nei/guihook/GuiContainerManager.splitTooltipByPage (Ljava/util/List;)Ljava/util/List;
    ASTORE 4
   L2
    LINENUMBER 621 L2
    GETSTATIC codechicken/nei/guihook/GuiContainerManager.tooltipPage : I
    ALOAD 4
    INVOKEINTERFACE java/util/List.size ()I
    IF_ICMPGE L3
    GETSTATIC codechicken/nei/guihook/GuiContainerManager.tooltipPage : I
    GOTO L4
   L3
   FRAME FULL [net/minecraft/client/gui/FontRenderer I I java/util/List java/util/List] []
    ICONST_0
   L4
   FRAME FULL [net/minecraft/client/gui/FontRenderer I I java/util/List java/util/List] [I]
    PUTSTATIC codechicken/nei/guihook/GuiContainerManager.tooltipPage : I
   L5
    LINENUMBER 622 L5
    ALOAD 4
    INVOKEINTERFACE java/util/List.size ()I
    ICONST_1
    IF_ICMPLE L6
   L7
    LINENUMBER 623 L7
    ALOAD 4
    GETSTATIC codechicken/nei/guihook/GuiContainerManager.tooltipPage : I
    INVOKEINTERFACE java/util/List.get (I)Ljava/lang/Object;
    CHECKCAST java/util/List
    NEW java/lang/StringBuilder
    DUP
    INVOKESPECIAL java/lang/StringBuilder.<init> ()V
    GETSTATIC net/minecraft/util/EnumChatFormatting.ITALIC : Lnet/minecraft/util/EnumChatFormatting;
    INVOKEVIRTUAL java/lang/StringBuilder.append (Ljava/lang/Object;)Ljava/lang/StringBuilder;
    LDC "inventory.tooltip.page"
    ICONST_3
    ANEWARRAY java/lang/Object
    DUP
    ICONST_0
    GETSTATIC codechicken/nei/guihook/GuiContainerManager.tooltipPage : I
    ICONST_1
    IADD
   L8
    LINENUMBER 626 L8
    INVOKESTATIC java/lang/Integer.valueOf (I)Ljava/lang/Integer;
    AASTORE
    DUP
    ICONST_1
    ALOAD 4
   L9
    LINENUMBER 627 L9
    INVOKEINTERFACE java/util/List.size ()I
    INVOKESTATIC java/lang/Integer.valueOf (I)Ljava/lang/Integer;
    AASTORE
    DUP
    ICONST_2
    LDC "gui.next_tooltip"
   L10
    LINENUMBER 628 L10
    INVOKESTATIC codechicken/nei/NEIClientConfig.getKeyName (Ljava/lang/String;)Ljava/lang/String;
    AASTORE
   L11
    LINENUMBER 624 L11
    INVOKESTATIC codechicken/nei/NEIClientUtils.translate (Ljava/lang/String;[Ljava/lang/Object;)Ljava/lang/String;
    INVOKEVIRTUAL java/lang/StringBuilder.append (Ljava/lang/String;)Ljava/lang/StringBuilder;
    INVOKEVIRTUAL java/lang/StringBuilder.toString ()Ljava/lang/String;
   L12
    LINENUMBER 623 L12
    INVOKEINTERFACE java/util/List.add (Ljava/lang/Object;)Z
    POP
   L6
    LINENUMBER 630 L6
   FRAME FULL [net/minecraft/client/gui/FontRenderer I I java/util/List java/util/List] []
    ALOAD 0
    ILOAD 1
    ILOAD 2
    ALOAD 4
    GETSTATIC codechicken/nei/guihook/GuiContainerManager.tooltipPage : I
    INVOKEINTERFACE java/util/List.get (I)Ljava/lang/Object;
    CHECKCAST java/util/List
    INVOKESTATIC codechicken/lib/gui/GuiDraw.drawMultilineTip (Lnet/minecraft/client/gui/FontRenderer;IILjava/util/List;)V
   L13
    LINENUMBER 631 L13
    RETURN
   L14
    LOCALVARIABLE font Lnet/minecraft/client/gui/FontRenderer; L0 L14 0
    LOCALVARIABLE x I L0 L14 1
    LOCALVARIABLE y I L0 L14 2
    LOCALVARIABLE list Ljava/util/List; L0 L14 3
    // signature Ljava/util/List<Ljava/lang/String;>;
    // declaration: java.util.List<java.lang.String>
    LOCALVARIABLE tooltips Ljava/util/List; L2 L14 4
    // signature Ljava/util/List<Ljava/util/List<Ljava/lang/String;>;>;
    // declaration: java.util.List<java.util.List<java.lang.String>>
    MAXSTACK = 8
    MAXLOCALS = 5

  // access flags 0x9
  // signature (Ljava/util/List<Ljava/lang/String;>;)Ljava/util/List<Ljava/util/List<Ljava/lang/String;>;>;
  // declaration: java.util.List<java.util.List<java.lang.String>> splitTooltipByPage(java.util.List<java.lang.String>)
  public static splitTooltipByPage(Ljava/util/List;)Ljava/util/List;
   L0
    LINENUMBER 634 L0
    NEW java/util/ArrayList
    DUP
    INVOKESPECIAL java/util/ArrayList.<init> ()V
    ASTORE 1
   L1
    LINENUMBER 635 L1
    NEW java/util/ArrayList
    DUP
    INVOKESPECIAL java/util/ArrayList.<init> ()V
    ASTORE 2
   L2
    LINENUMBER 636 L2
    BIPUSH -2
    ISTORE 3
   L3
    LINENUMBER 637 L3
    ICONST_0
    ISTORE 4
   L4
   FRAME FULL [java/util/List java/util/ArrayList java/util/ArrayList I I] []
    ILOAD 4
    ALOAD 0
    INVOKEINTERFACE java/util/List.size ()I
    IF_ICMPGE L5
   L6
    LINENUMBER 638 L6
    ALOAD 0
    ILOAD 4
    INVOKEINTERFACE java/util/List.get (I)Ljava/lang/Object;
    CHECKCAST java/lang/String
    ASTORE 5
   L7
    LINENUMBER 639 L7
    ALOAD 5
    INVOKESTATIC codechicken/lib/gui/GuiDraw.getTipLine (Ljava/lang/String;)Lcodechicken/lib/gui/GuiDraw$ITooltipLineHandler;
    ASTORE 6
   L8
    LINENUMBER 640 L8
    ALOAD 6
    IFNULL L9
    ALOAD 6
    INVOKEINTERFACE codechicken/lib/gui/GuiDraw$ITooltipLineHandler.getSize ()Ljava/awt/Dimension;
    GETFIELD java/awt/Dimension.height : I
    GOTO L10
   L9
    LINENUMBER 641 L9
   FRAME FULL [java/util/List java/util/ArrayList java/util/ArrayList I I java/lang/String codechicken/lib/gui/GuiDraw$ITooltipLineHandler] []
    ALOAD 5
    LDC "\u00a7h"
    INVOKEVIRTUAL java/lang/String.endsWith (Ljava/lang/String;)Z
    IFEQ L11
    ILOAD 4
    ICONST_1
    IADD
    ALOAD 0
    INVOKEINTERFACE java/util/List.size ()I
    IF_ICMPGE L11
    BIPUSH 12
    GOTO L10
   L11
   FRAME FULL [java/util/List java/util/ArrayList java/util/ArrayList I I java/lang/String codechicken/lib/gui/GuiDraw$ITooltipLineHandler] []
    BIPUSH 10
   L10
   FRAME FULL [java/util/List java/util/ArrayList java/util/ArrayList I I java/lang/String codechicken/lib/gui/GuiDraw$ITooltipLineHandler] [I]
    ISTORE 7
   L12
    LINENUMBER 642 L12
    ILOAD 3
    ILOAD 7
    IADD
    INVOKESTATIC codechicken/lib/gui/GuiDraw.displaySize ()Ljava/awt/Dimension;
    GETFIELD java/awt/Dimension.height : I
    BIPUSH 16
    ISUB
    BIPUSH 10
    ISUB
    IF_ICMPGT L13
   L14
    LINENUMBER 644 L14
    ILOAD 3
    ILOAD 7
    IADD
    ISTORE 3
    GOTO L15
   L13
    LINENUMBER 646 L13
   FRAME FULL [java/util/List java/util/ArrayList java/util/ArrayList I I java/lang/String codechicken/lib/gui/GuiDraw$ITooltipLineHandler I] []
    ALOAD 1
    NEW java/util/ArrayList
    DUP
    ALOAD 2
    INVOKESPECIAL java/util/ArrayList.<init> (Ljava/util/Collection;)V
    INVOKEINTERFACE java/util/List.add (Ljava/lang/Object;)Z
    POP
   L16
    LINENUMBER 647 L16
    ALOAD 2
    INVOKEINTERFACE java/util/List.clear ()V
   L17
    LINENUMBER 648 L17
    BIPUSH -2
    ISTORE 3
   L15
    LINENUMBER 650 L15
   FRAME FULL [java/util/List java/util/ArrayList java/util/ArrayList I I java/lang/String codechicken/lib/gui/GuiDraw$ITooltipLineHandler I] []
    ALOAD 2
    ALOAD 5
    INVOKEINTERFACE java/util/List.add (Ljava/lang/Object;)Z
    POP
   L18
    LINENUMBER 637 L18
    IINC 4 1
    GOTO L4
   L5
    LINENUMBER 652 L5
   FRAME FULL [java/util/List java/util/ArrayList java/util/ArrayList I I] []
    ALOAD 2
    INVOKEINTERFACE java/util/List.isEmpty ()Z
    IFNE L19
   L20
    LINENUMBER 653 L20
    ALOAD 1
    ALOAD 2
    INVOKEINTERFACE java/util/List.add (Ljava/lang/Object;)Z
    POP
   L19
    LINENUMBER 655 L19
   FRAME FULL [java/util/List java/util/ArrayList java/util/ArrayList I I] []
    ALOAD 1
    ARETURN
   L21
    LOCALVARIABLE text Ljava/lang/String; L7 L18 5
    LOCALVARIABLE line Lcodechicken/lib/gui/GuiDraw$ITooltipLineHandler; L8 L18 6
    LOCALVARIABLE lineHeight I L12 L18 7
    LOCALVARIABLE i I L4 L5 4
    LOCALVARIABLE list Ljava/util/List; L0 L21 0
    // signature Ljava/util/List<Ljava/lang/String;>;
    // declaration: java.util.List<java.lang.String>
    LOCALVARIABLE ret Ljava/util/List; L1 L21 1
    // signature Ljava/util/List<Ljava/util/List<Ljava/lang/String;>;>;
    // declaration: java.util.List<java.util.List<java.lang.String>>
    LOCALVARIABLE tmp Ljava/util/List; L2 L21 2
    // signature Ljava/util/List<Ljava/lang/String;>;
    // declaration: java.util.List<java.lang.String>
    LOCALVARIABLE height I L3 L21 3
    MAXSTACK = 4
    MAXLOCALS = 8

  // access flags 0x9
  public static shouldShowTooltip(Lnet/minecraft/client/gui/inventory/GuiContainer;)Z
   L0
    LINENUMBER 659 L0
    ALOAD 0
    IFNONNULL L1
    ICONST_0
    IRETURN
   L1
    LINENUMBER 660 L1
   FRAME FULL [net/minecraft/client/gui/inventory/GuiContainer] []
    GETSTATIC codechicken/nei/guihook/GuiContainerManager.objectHandlers : Ljava/util/LinkedList;
    INVOKEVIRTUAL java/util/LinkedList.iterator ()Ljava/util/Iterator;
    ASTORE 1
   L2
   FRAME FULL [net/minecraft/client/gui/inventory/GuiContainer java/util/Iterator] []
    ALOAD 1
    INVOKEINTERFACE java/util/Iterator.hasNext ()Z
    IFEQ L3
    ALOAD 1
    INVOKEINTERFACE java/util/Iterator.next ()Ljava/lang/Object;
    CHECKCAST codechicken/nei/guihook/IContainerObjectHandler
    ASTORE 2
   L4
    ALOAD 2
    ALOAD 0
    INVOKEINTERFACE codechicken/nei/guihook/IContainerObjectHandler.shouldShowTooltip (Lnet/minecraft/client/gui/inventory/GuiContainer;)Z
    IFNE L5
    ICONST_0
    IRETURN
   L5
   FRAME FULL [net/minecraft/client/gui/inventory/GuiContainer java/util/Iterator codechicken/nei/guihook/IContainerObjectHandler] []
    GOTO L2
   L3
    LINENUMBER 662 L3
   FRAME FULL [net/minecraft/client/gui/inventory/GuiContainer java/util/Iterator] []
    ALOAD 0
    GETFIELD net/minecraft/client/gui/inventory/GuiContainer.mc : Lnet/minecraft/client/Minecraft;
    GETFIELD net/minecraft/client/Minecraft.thePlayer : Lnet/minecraft/client/entity/EntityClientPlayerMP;
    GETFIELD net/minecraft/client/entity/EntityClientPlayerMP.inventory : Lnet/minecraft/entity/player/InventoryPlayer;
    INVOKEVIRTUAL net/minecraft/entity/player/InventoryPlayer.getItemStack ()Lnet/minecraft/item/ItemStack;
    IFNONNULL L6
    ICONST_1
    GOTO L7
   L6
   FRAME FULL [net/minecraft/client/gui/inventory/GuiContainer java/util/Iterator] []
    ICONST_0
   L7
   FRAME FULL [net/minecraft/client/gui/inventory/GuiContainer java/util/Iterator] [I]
    IRETURN
   L8
    LOCALVARIABLE handler Lcodechicken/nei/guihook/IContainerObjectHandler; L4 L5 2
    LOCALVARIABLE window Lnet/minecraft/client/gui/inventory/GuiContainer; L0 L8 0
    MAXSTACK = 2
    MAXLOCALS = 3

  // access flags 0x9
  // signature (Ljava/util/List<Ljava/lang/String;>;Lnet/minecraft/item/ItemStack;)V
  // declaration: void applyItemCountDetails(java.util.List<java.lang.String>, net.minecraft.item.ItemStack)
  public static applyItemCountDetails(Ljava/util/List;Lnet/minecraft/item/ItemStack;)V
   L0
    LINENUMBER 666 L0
    ALOAD 1
    GETFIELD net/minecraft/item/ItemStack.stackSize : I
    LDC 2147483647
    IF_ICMPEQ L1
    INVOKESTATIC codechicken/nei/NEIClientUtils.shiftKey ()Z
    IFEQ L1
   L2
    LINENUMBER 667 L2
    ALOAD 1
    INVOKESTATIC codechicken/nei/guihook/GuiContainerManager.itemCountDetails (Lnet/minecraft/item/ItemStack;)Ljava/lang/String;
    ASTORE 2
   L3
    LINENUMBER 669 L3
    ALOAD 2
    IFNULL L1
   L4
    LINENUMBER 670 L4
    ALOAD 0
    NEW java/lang/StringBuilder
    DUP
    INVOKESPECIAL java/lang/StringBuilder.<init> ()V
    GETSTATIC net/minecraft/util/EnumChatFormatting.GRAY : Lnet/minecraft/util/EnumChatFormatting;
    INVOKEVIRTUAL java/lang/StringBuilder.append (Ljava/lang/Object;)Ljava/lang/StringBuilder;
    ALOAD 2
    INVOKEVIRTUAL java/lang/StringBuilder.append (Ljava/lang/String;)Ljava/lang/StringBuilder;
    GETSTATIC net/minecraft/util/EnumChatFormatting.RESET : Lnet/minecraft/util/EnumChatFormatting;
    INVOKEVIRTUAL java/lang/StringBuilder.append (Ljava/lang/Object;)Ljava/lang/StringBuilder;
    INVOKEVIRTUAL java/lang/StringBuilder.toString ()Ljava/lang/String;
    ICONST_0
    ANEWARRAY java/lang/Object
    INVOKESTATIC java/lang/String.format (Ljava/lang/String;[Ljava/lang/Object;)Ljava/lang/String;
    INVOKEINTERFACE java/util/List.add (Ljava/lang/Object;)Z
    POP
   L1
    LINENUMBER 673 L1
   FRAME FULL [java/util/List net/minecraft/item/ItemStack] []
    RETURN
   L5
    LOCALVARIABLE itemCount Ljava/lang/String; L3 L1 2
    LOCALVARIABLE tooltip Ljava/util/List; L0 L5 0
    // signature Ljava/util/List<Ljava/lang/String;>;
    // declaration: java.util.List<java.lang.String>
    LOCALVARIABLE stack Lnet/minecraft/item/ItemStack; L0 L5 1
    MAXSTACK = 3
    MAXLOCALS = 3

  // access flags 0x9
  public static incrementTooltipPage()V
   L0
    LINENUMBER 676 L0
    GETSTATIC codechicken/nei/guihook/GuiContainerManager.tooltipPage : I
    ICONST_1
    IADD
    PUTSTATIC codechicken/nei/guihook/GuiContainerManager.tooltipPage : I
   L1
    LINENUMBER 677 L1
    RETURN
    MAXSTACK = 2
    MAXLOCALS = 0

  // access flags 0x1
  public renderSlotUnderlay(Lnet/minecraft/inventory/Slot;)V
   L0
    LINENUMBER 680 L0
    GETSTATIC codechicken/nei/guihook/GuiContainerManager.drawHandlers : Ljava/util/LinkedList;
    INVOKEVIRTUAL java/util/LinkedList.iterator ()Ljava/util/Iterator;
    ASTORE 2
   L1
   FRAME FULL [codechicken/nei/guihook/GuiContainerManager net/minecraft/inventory/Slot java/util/Iterator] []
    ALOAD 2
    INVOKEINTERFACE java/util/Iterator.hasNext ()Z
    IFEQ L2
    ALOAD 2
    INVOKEINTERFACE java/util/Iterator.next ()Ljava/lang/Object;
    CHECKCAST codechicken/nei/guihook/IContainerDrawHandler
    ASTORE 3
   L3
    ALOAD 3
    ALOAD 0
    GETFIELD codechicken/nei/guihook/GuiContainerManager.window : Lnet/minecraft/client/gui/inventory/GuiContainer;
    ALOAD 1
    INVOKEINTERFACE codechicken/nei/guihook/IContainerDrawHandler.renderSlotUnderlay (Lnet/minecraft/client/gui/inventory/GuiContainer;Lnet/minecraft/inventory/Slot;)V
   L4
    GOTO L1
   L2
    LINENUMBER 681 L2
   FRAME FULL [codechicken/nei/guihook/GuiContainerManager net/minecraft/inventory/Slot java/util/Iterator] []
    RETURN
   L5
    LOCALVARIABLE drawHandler Lcodechicken/nei/guihook/IContainerDrawHandler; L3 L4 3
    LOCALVARIABLE this Lcodechicken/nei/guihook/GuiContainerManager; L0 L5 0
    LOCALVARIABLE slot Lnet/minecraft/inventory/Slot; L0 L5 1
    MAXSTACK = 3
    MAXLOCALS = 4

  // access flags 0x1
  public renderSlotOverlay(Lnet/minecraft/inventory/Slot;)V
   L0
    LINENUMBER 684 L0
    GETSTATIC codechicken/nei/guihook/GuiContainerManager.drawHandlers : Ljava/util/LinkedList;
    INVOKEVIRTUAL java/util/LinkedList.iterator ()Ljava/util/Iterator;
    ASTORE 2
   L1
   FRAME FULL [codechicken/nei/guihook/GuiContainerManager net/minecraft/inventory/Slot java/util/Iterator] []
    ALOAD 2
    INVOKEINTERFACE java/util/Iterator.hasNext ()Z
    IFEQ L2
    ALOAD 2
    INVOKEINTERFACE java/util/Iterator.next ()Ljava/lang/Object;
    CHECKCAST codechicken/nei/guihook/IContainerDrawHandler
    ASTORE 3
   L3
    ALOAD 3
    ALOAD 0
    GETFIELD codechicken/nei/guihook/GuiContainerManager.window : Lnet/minecraft/client/gui/inventory/GuiContainer;
    ALOAD 1
    INVOKEINTERFACE codechicken/nei/guihook/IContainerDrawHandler.renderSlotOverlay (Lnet/minecraft/client/gui/inventory/GuiContainer;Lnet/minecraft/inventory/Slot;)V
   L4
    GOTO L1
   L2
    LINENUMBER 685 L2
   FRAME FULL [codechicken/nei/guihook/GuiContainerManager net/minecraft/inventory/Slot java/util/Iterator] []
    SIPUSH 3008
    INVOKESTATIC org/lwjgl/opengl/GL11.glEnable (I)V
   L5
    LINENUMBER 686 L5
    RETURN
   L6
    LOCALVARIABLE drawHandler Lcodechicken/nei/guihook/IContainerDrawHandler; L3 L4 3
    LOCALVARIABLE this Lcodechicken/nei/guihook/GuiContainerManager; L0 L6 0
    LOCALVARIABLE slot Lnet/minecraft/inventory/Slot; L0 L6 1
    MAXSTACK = 3
    MAXLOCALS = 4

  // access flags 0x1
  public objectUnderMouse(II)Z
   L0
    LINENUMBER 692 L0
    GETSTATIC codechicken/nei/guihook/GuiContainerManager.objectHandlers : Ljava/util/LinkedList;
    INVOKEVIRTUAL java/util/LinkedList.iterator ()Ljava/util/Iterator;
    ASTORE 3
   L1
   FRAME FULL [codechicken/nei/guihook/GuiContainerManager I I java/util/Iterator] []
    ALOAD 3
    INVOKEINTERFACE java/util/Iterator.hasNext ()Z
    IFEQ L2
    ALOAD 3
    INVOKEINTERFACE java/util/Iterator.next ()Ljava/lang/Object;
    CHECKCAST codechicken/nei/guihook/IContainerObjectHandler
    ASTORE 4
   L3
    LINENUMBER 693 L3
    ALOAD 4
    ALOAD 0
    GETFIELD codechicken/nei/guihook/GuiContainerManager.window : Lnet/minecraft/client/gui/inventory/GuiContainer;
    ILOAD 1
    ILOAD 2
    INVOKEINTERFACE codechicken/nei/guihook/IContainerObjectHandler.objectUnderMouse (Lnet/minecraft/client/gui/inventory/GuiContainer;II)Z
    IFEQ L4
    ICONST_1
    IRETURN
   L4
   FRAME FULL [codechicken/nei/guihook/GuiContainerManager I I java/util/Iterator codechicken/nei/guihook/IContainerObjectHandler] []
    GOTO L1
   L2
    LINENUMBER 695 L2
   FRAME FULL [codechicken/nei/guihook/GuiContainerManager I I java/util/Iterator] []
    ICONST_0
    IRETURN
   L5
    LOCALVARIABLE objectHandler Lcodechicken/nei/guihook/IContainerObjectHandler; L3 L4 4
    LOCALVARIABLE this Lcodechicken/nei/guihook/GuiContainerManager; L0 L5 0
    LOCALVARIABLE mousex I L0 L5 1
    LOCALVARIABLE mousey I L0 L5 2
    MAXSTACK = 4
    MAXLOCALS = 5

  // access flags 0x1
  public handleMouseClick(Lnet/minecraft/inventory/Slot;III)V
   L0
    LINENUMBER 699 L0
    GETSTATIC codechicken/nei/guihook/GuiContainerManager.slotClickHandlers : Ljava/util/LinkedList;
    INVOKEVIRTUAL java/util/LinkedList.iterator ()Ljava/util/Iterator;
    ASTORE 5
   L1
   FRAME FULL [codechicken/nei/guihook/GuiContainerManager net/minecraft/inventory/Slot I I I java/util/Iterator] []
    ALOAD 5
    INVOKEINTERFACE java/util/Iterator.hasNext ()Z
    IFEQ L2
    ALOAD 5
    INVOKEINTERFACE java/util/Iterator.next ()Ljava/lang/Object;
    CHECKCAST codechicken/nei/guihook/IContainerSlotClickHandler
    ASTORE 6
   L3
    LINENUMBER 700 L3
    ALOAD 6
    ALOAD 0
    GETFIELD codechicken/nei/guihook/GuiContainerManager.window : Lnet/minecraft/client/gui/inventory/GuiContainer;
    ILOAD 2
    ILOAD 3
    ALOAD 1
    ILOAD 4
    INVOKEINTERFACE codechicken/nei/guihook/IContainerSlotClickHandler.beforeSlotClick (Lnet/minecraft/client/gui/inventory/GuiContainer;IILnet/minecraft/inventory/Slot;I)V
   L4
    GOTO L1
   L2
    LINENUMBER 702 L2
   FRAME FULL [codechicken/nei/guihook/GuiContainerManager net/minecraft/inventory/Slot I I I java/util/Iterator] []
    ICONST_0
    ISTORE 5
   L5
    LINENUMBER 703 L5
    GETSTATIC codechicken/nei/guihook/GuiContainerManager.slotClickHandlers : Ljava/util/LinkedList;
    INVOKEVIRTUAL java/util/LinkedList.iterator ()Ljava/util/Iterator;
    ASTORE 6
   L6
   FRAME FULL [codechicken/nei/guihook/GuiContainerManager net/minecraft/inventory/Slot I I I I java/util/Iterator] []
    ALOAD 6
    INVOKEINTERFACE java/util/Iterator.hasNext ()Z
    IFEQ L7
    ALOAD 6
    INVOKEINTERFACE java/util/Iterator.next ()Ljava/lang/Object;
    CHECKCAST codechicken/nei/guihook/IContainerSlotClickHandler
    ASTORE 7
   L8
    LINENUMBER 704 L8
    ALOAD 7
    ALOAD 0
    GETFIELD codechicken/nei/guihook/GuiContainerManager.window : Lnet/minecraft/client/gui/inventory/GuiContainer;
    ILOAD 2
    ILOAD 3
    ALOAD 1
    ILOAD 4
    ILOAD 5
    INVOKEINTERFACE codechicken/nei/guihook/IContainerSlotClickHandler.handleSlotClick (Lnet/minecraft/client/gui/inventory/GuiContainer;IILnet/minecraft/inventory/Slot;IZ)Z
    ISTORE 5
   L9
    GOTO L6
   L7
    LINENUMBER 706 L7
   FRAME FULL [codechicken/nei/guihook/GuiContainerManager net/minecraft/inventory/Slot I I I I java/util/Iterator] []
    GETSTATIC codechicken/nei/guihook/GuiContainerManager.slotClickHandlers : Ljava/util/LinkedList;
    INVOKEVIRTUAL java/util/LinkedList.iterator ()Ljava/util/Iterator;
    ASTORE 6
   L10
   FRAME FULL [codechicken/nei/guihook/GuiContainerManager net/minecraft/inventory/Slot I I I I java/util/Iterator] []
    ALOAD 6
    INVOKEINTERFACE java/util/Iterator.hasNext ()Z
    IFEQ L11
    ALOAD 6
    INVOKEINTERFACE java/util/Iterator.next ()Ljava/lang/Object;
    CHECKCAST codechicken/nei/guihook/IContainerSlotClickHandler
    ASTORE 7
   L12
    LINENUMBER 707 L12
    ALOAD 7
    ALOAD 0
    GETFIELD codechicken/nei/guihook/GuiContainerManager.window : Lnet/minecraft/client/gui/inventory/GuiContainer;
    ILOAD 2
    ILOAD 3
    ALOAD 1
    ILOAD 4
    INVOKEINTERFACE codechicken/nei/guihook/IContainerSlotClickHandler.afterSlotClick (Lnet/minecraft/client/gui/inventory/GuiContainer;IILnet/minecraft/inventory/Slot;I)V
   L13
    GOTO L10
   L11
    LINENUMBER 708 L11
   FRAME FULL [codechicken/nei/guihook/GuiContainerManager net/minecraft/inventory/Slot I I I I java/util/Iterator] []
    RETURN
   L14
    LOCALVARIABLE handler Lcodechicken/nei/guihook/IContainerSlotClickHandler; L3 L4 6
    LOCALVARIABLE handler Lcodechicken/nei/guihook/IContainerSlotClickHandler; L8 L9 7
    LOCALVARIABLE handler Lcodechicken/nei/guihook/IContainerSlotClickHandler; L12 L13 7
    LOCALVARIABLE this Lcodechicken/nei/guihook/GuiContainerManager; L0 L14 0
    LOCALVARIABLE slot Lnet/minecraft/inventory/Slot; L0 L14 1
    LOCALVARIABLE slotIndex I L0 L14 2
    LOCALVARIABLE button I L0 L14 3
    LOCALVARIABLE modifier I L0 L14 4
    LOCALVARIABLE eventHandled Z L5 L14 5
    MAXSTACK = 7
    MAXLOCALS = 8

  // access flags 0x1
  public handleKeyboardInput()V
    TRYCATCHBLOCK L0 L1 L2 java/lang/IndexOutOfBoundsException
   L3
    LINENUMBER 713 L3
    INVOKESTATIC org/lwjgl/input/Keyboard.getEventKey ()I
    ISTORE 1
   L4
    LINENUMBER 714 L4
    INVOKESTATIC org/lwjgl/input/Keyboard.getEventCharacter ()C
    ISTORE 2
   L5
    LINENUMBER 715 L5
    INVOKESTATIC org/lwjgl/input/Keyboard.getEventKeyState ()Z
    IFNE L0
    ILOAD 1
    IFNE L6
    ILOAD 2
    INVOKESTATIC java/lang/Character.isDefined (C)Z
    IFEQ L6
   L0
    LINENUMBER 717 L0
   FRAME FULL [codechicken/nei/guihook/GuiContainerManager I I] []
    ALOAD 0
    ILOAD 2
    ILOAD 1
    INVOKEVIRTUAL codechicken/nei/guihook/GuiContainerManager.keyTyped (CI)V
   L1
    LINENUMBER 721 L1
    GOTO L6
   L2
    LINENUMBER 718 L2
   FRAME FULL [codechicken/nei/guihook/GuiContainerManager I I] [java/lang/IndexOutOfBoundsException]
    ASTORE 3
   L7
    LINENUMBER 719 L7
    GETSTATIC java/lang/System.err : Ljava/io/PrintStream;
    NEW java/lang/StringBuilder
    DUP
    INVOKESPECIAL java/lang/StringBuilder.<init> ()V
    LDC "Caught out of bounds exception pressing "
    INVOKEVIRTUAL java/lang/StringBuilder.append (Ljava/lang/String;)Ljava/lang/StringBuilder;
    ILOAD 2
    INVOKEVIRTUAL java/lang/StringBuilder.append (C)Ljava/lang/StringBuilder;
    LDC " "
    INVOKEVIRTUAL java/lang/StringBuilder.append (Ljava/lang/String;)Ljava/lang/StringBuilder;
    ILOAD 1
    INVOKEVIRTUAL java/lang/StringBuilder.append (I)Ljava/lang/StringBuilder;
    INVOKEVIRTUAL java/lang/StringBuilder.toString ()Ljava/lang/String;
    INVOKEVIRTUAL java/io/PrintStream.println (Ljava/lang/String;)V
   L8
    LINENUMBER 720 L8
    ALOAD 3
    INVOKEVIRTUAL java/lang/IndexOutOfBoundsException.printStackTrace ()V
   L6
    LINENUMBER 724 L6
   FRAME FULL [codechicken/nei/guihook/GuiContainerManager I I] []
    ALOAD 0
    GETFIELD codechicken/nei/guihook/GuiContainerManager.window : Lnet/minecraft/client/gui/inventory/GuiContainer;
    GETFIELD net/minecraft/client/gui/inventory/GuiContainer.mc : Lnet/minecraft/client/Minecraft;
    INVOKEVIRTUAL net/minecraft/client/Minecraft.func_152348_aa ()V
   L9
    LINENUMBER 725 L9
    RETURN
   L10
    LOCALVARIABLE e Ljava/lang/IndexOutOfBoundsException; L7 L6 3
    LOCALVARIABLE this Lcodechicken/nei/guihook/GuiContainerManager; L3 L10 0
    LOCALVARIABLE k I L4 L10 1
    LOCALVARIABLE c C L5 L10 2
    MAXSTACK = 3
    MAXLOCALS = 4

  // access flags 0x1
  public keyTyped(CI)V
   L0
    LINENUMBER 728 L0
    ALOAD 0
    ILOAD 1
    ILOAD 2
    INVOKEVIRTUAL codechicken/nei/guihook/GuiContainerManager.firstKeyTyped (CI)Z
    IFEQ L1
    RETURN
   L1
    LINENUMBER 730 L1
   FRAME FULL [codechicken/nei/guihook/GuiContainerManager I I] []
    ALOAD 0
    GETFIELD codechicken/nei/guihook/GuiContainerManager.window : Lnet/minecraft/client/gui/inventory/GuiContainer;
    ILOAD 1
    ILOAD 2
    INVOKESTATIC codechicken/nei/guihook/GuiContainerManager.callKeyTyped (Lnet/minecraft/client/gui/inventory/GuiContainer;CI)V
   L2
    LINENUMBER 731 L2
    RETURN
   L3
    LOCALVARIABLE this Lcodechicken/nei/guihook/GuiContainerManager; L0 L3 0
    LOCALVARIABLE c C L0 L3 1
    LOCALVARIABLE k I L0 L3 2
    MAXSTACK = 3
    MAXLOCALS = 3

  // access flags 0x9
  public static callKeyTyped(Lnet/minecraft/client/gui/inventory/GuiContainer;CI)V
    ALOAD 0
    ILOAD 1
    ILOAD 2
    INVOKEVIRTUAL net/minecraft/client/gui/inventory/GuiContainer.public_func_73869_a (CI)V
    RETURN
    MAXSTACK = 3
    MAXLOCALS = 3

  // access flags 0x1
  public drawSlotItem(Lnet/minecraft/inventory/Slot;Lnet/minecraft/item/ItemStack;IILjava/lang/String;)V
    TRYCATCHBLOCK L0 L1 L2 java/lang/Exception
   L3
    LINENUMBER 742 L3
    LDC 32826
    INVOKESTATIC org/lwjgl/opengl/GL11.glGetBoolean (I)Z
    ISTORE 6
   L4
    LINENUMBER 743 L4
    GETSTATIC codechicken/nei/guihook/GuiContainerManager.drawItems : Lnet/minecraft/client/renderer/entity/RenderItem;
    DUP
    GETFIELD net/minecraft/client/renderer/entity/RenderItem.zLevel : F
    LDC 100.0
    FADD
    DUP_X1
    PUTFIELD net/minecraft/client/renderer/entity/RenderItem.zLevel : F
    FSTORE 7
   L5
    LINENUMBER 745 L5
    GETSTATIC codechicken/nei/guihook/GuiContainerManager.renderingErrorItems : Lcodechicken/nei/ItemStackSet;
    ALOAD 2
    INVOKEVIRTUAL codechicken/nei/ItemStackSet.contains (Lnet/minecraft/item/ItemStack;)Z
    IFNE L6
   L0
    LINENUMBER 747 L0
    ALOAD 0
    GETFIELD codechicken/nei/guihook/GuiContainerManager.window : Lnet/minecraft/client/gui/inventory/GuiContainer;
    INSTANCEOF codechicken/nei/guihook/IGuiSlotDraw
    IFEQ L7
   L8
    LINENUMBER 748 L8
    ALOAD 0
    GETFIELD codechicken/nei/guihook/GuiContainerManager.window : Lnet/minecraft/client/gui/inventory/GuiContainer;
    CHECKCAST codechicken/nei/guihook/IGuiSlotDraw
    ALOAD 1
    ALOAD 2
    ILOAD 3
    ILOAD 4
    ALOAD 5
    INVOKEINTERFACE codechicken/nei/guihook/IGuiSlotDraw.drawSlotItem (Lnet/minecraft/inventory/Slot;Lnet/minecraft/item/ItemStack;IILjava/lang/String;)V
    GOTO L1
   L7
    LINENUMBER 751 L7
   FRAME FULL [codechicken/nei/guihook/GuiContainerManager net/minecraft/inventory/Slot net/minecraft/item/ItemStack I I java/lang/String I F] []
    ALOAD 5
    IFNONNULL L9
   L10
    LINENUMBER 752 L10
    ALOAD 2
    IFNULL L11
    ALOAD 2
    GETFIELD net/minecraft/item/ItemStack.stackSize : I
    ICONST_1
    IF_ICMPLE L11
    ALOAD 2
    GETFIELD net/minecraft/item/ItemStack.stackSize : I
    INVOKESTATIC java/lang/String.valueOf (I)Ljava/lang/String;
    GOTO L12
   L11
   FRAME FULL [codechicken/nei/guihook/GuiContainerManager net/minecraft/inventory/Slot net/minecraft/item/ItemStack I I java/lang/String I F] []
    LDC ""
   L12
   FRAME FULL [codechicken/nei/guihook/GuiContainerManager net/minecraft/inventory/Slot net/minecraft/item/ItemStack I I java/lang/String I F] [java/lang/String]
    ASTORE 5
   L9
    LINENUMBER 755 L9
   FRAME FULL [codechicken/nei/guihook/GuiContainerManager net/minecraft/inventory/Slot net/minecraft/item/ItemStack I I java/lang/String I F] []
    GETSTATIC codechicken/nei/guihook/GuiContainerManager.drawItems : Lnet/minecraft/client/renderer/entity/RenderItem;
    GETSTATIC codechicken/lib/gui/GuiDraw.fontRenderer : Lnet/minecraft/client/gui/FontRenderer;
    GETSTATIC codechicken/lib/gui/GuiDraw.renderEngine : Lnet/minecraft/client/renderer/texture/TextureManager;
    ALOAD 2
    ILOAD 3
    ILOAD 4
    INVOKEVIRTUAL net/minecraft/client/renderer/entity/RenderItem.renderItemAndEffectIntoGUI (Lnet/minecraft/client/gui/FontRenderer;Lnet/minecraft/client/renderer/texture/TextureManager;Lnet/minecraft/item/ItemStack;II)V
   L13
    LINENUMBER 756 L13
    GETSTATIC codechicken/nei/guihook/GuiContainerManager.drawItems : Lnet/minecraft/client/renderer/entity/RenderItem;
    GETSTATIC codechicken/lib/gui/GuiDraw.fontRenderer : Lnet/minecraft/client/gui/FontRenderer;
    GETSTATIC codechicken/lib/gui/GuiDraw.renderEngine : Lnet/minecraft/client/renderer/texture/TextureManager;
    ALOAD 2
    ILOAD 3
    ILOAD 4
    ALOAD 5
    INVOKEVIRTUAL net/minecraft/client/renderer/entity/RenderItem.renderItemOverlayIntoGUI (Lnet/minecraft/client/gui/FontRenderer;Lnet/minecraft/client/renderer/texture/TextureManager;Lnet/minecraft/item/ItemStack;IILjava/lang/String;)V
   L1
    LINENUMBER 767 L1
   FRAME FULL [codechicken/nei/guihook/GuiContainerManager net/minecraft/inventory/Slot net/minecraft/item/ItemStack I I java/lang/String I F] []
    GOTO L14
   L2
    LINENUMBER 758 L2
   FRAME FULL [codechicken/nei/guihook/GuiContainerManager net/minecraft/inventory/Slot net/minecraft/item/ItemStack I I java/lang/String I F] [java/lang/Exception]
    ASTORE 8
   L15
    LINENUMBER 759 L15
    ALOAD 8
    GETSTATIC codechicken/nei/guihook/GuiContainerManager.stackTraces : Ljava/util/HashSet;
    ALOAD 2
    INVOKESTATIC codechicken/nei/NEIClientUtils.reportErrorBuffered (Ljava/lang/Throwable;Ljava/util/Set;Lnet/minecraft/item/ItemStack;)V
   L16
    LINENUMBER 761 L16
    INVOKESTATIC codechicken/nei/guihook/GuiContainerManager.restoreMatrixStack ()V
   L17
    LINENUMBER 762 L17
    GETSTATIC net/minecraft/client/renderer/Tessellator.instance : Lnet/minecraft/client/renderer/Tessellator;
    GETFIELD net/minecraft/client/renderer/Tessellator.isDrawing : Z
    IFEQ L18
    GETSTATIC net/minecraft/client/renderer/Tessellator.instance : Lnet/minecraft/client/renderer/Tessellator;
    INVOKEVIRTUAL net/minecraft/client/renderer/Tessellator.draw ()I
    POP
   L18
    LINENUMBER 764 L18
   FRAME FULL [codechicken/nei/guihook/GuiContainerManager net/minecraft/inventory/Slot net/minecraft/item/ItemStack I I java/lang/String I F java/lang/Exception] []
    GETSTATIC codechicken/nei/guihook/GuiContainerManager.drawItems : Lnet/minecraft/client/renderer/entity/RenderItem;
    FLOAD 7
    PUTFIELD net/minecraft/client/renderer/entity/RenderItem.zLevel : F
   L19
    LINENUMBER 765 L19
    GETSTATIC codechicken/nei/guihook/GuiContainerManager.drawItems : Lnet/minecraft/client/renderer/entity/RenderItem;
    GETSTATIC codechicken/lib/gui/GuiDraw.fontRenderer : Lnet/minecraft/client/gui/FontRenderer;
    GETSTATIC codechicken/lib/gui/GuiDraw.renderEngine : Lnet/minecraft/client/renderer/texture/TextureManager;
    NEW net/minecraft/item/ItemStack
    DUP
    GETSTATIC net/minecraft/init/Blocks.fire : Lnet/minecraft/block/BlockFire;
    INVOKESPECIAL net/minecraft/item/ItemStack.<init> (Lnet/minecraft/block/Block;)V
    ILOAD 3
    ILOAD 4
    INVOKEVIRTUAL net/minecraft/client/renderer/entity/RenderItem.renderItemIntoGUI (Lnet/minecraft/client/gui/FontRenderer;Lnet/minecraft/client/renderer/texture/TextureManager;Lnet/minecraft/item/ItemStack;II)V
   L20
    LINENUMBER 766 L20
    GETSTATIC codechicken/nei/guihook/GuiContainerManager.renderingErrorItems : Lcodechicken/nei/ItemStackSet;
    ALOAD 2
    INVOKEVIRTUAL codechicken/nei/ItemStackSet.add (Lnet/minecraft/item/ItemStack;)V
   L21
    LINENUMBER 767 L21
    GOTO L14
   L6
    LINENUMBER 769 L6
   FRAME FULL [codechicken/nei/guihook/GuiContainerManager net/minecraft/inventory/Slot net/minecraft/item/ItemStack I I java/lang/String I F] []
    GETSTATIC codechicken/nei/guihook/GuiContainerManager.drawItems : Lnet/minecraft/client/renderer/entity/RenderItem;
    GETSTATIC codechicken/lib/gui/GuiDraw.fontRenderer : Lnet/minecraft/client/gui/FontRenderer;
    GETSTATIC codechicken/lib/gui/GuiDraw.renderEngine : Lnet/minecraft/client/renderer/texture/TextureManager;
    NEW net/minecraft/item/ItemStack
    DUP
    GETSTATIC net/minecraft/init/Blocks.fire : Lnet/minecraft/block/BlockFire;
    INVOKESPECIAL net/minecraft/item/ItemStack.<init> (Lnet/minecraft/block/Block;)V
    ILOAD 3
    ILOAD 4
    INVOKEVIRTUAL net/minecraft/client/renderer/entity/RenderItem.renderItemIntoGUI (Lnet/minecraft/client/gui/FontRenderer;Lnet/minecraft/client/renderer/texture/TextureManager;Lnet/minecraft/item/ItemStack;II)V
   L14
    LINENUMBER 772 L14
   FRAME FULL [codechicken/nei/guihook/GuiContainerManager net/minecraft/inventory/Slot net/minecraft/item/ItemStack I I java/lang/String I F] []
    ILOAD 6
    IFEQ L22
   L23
    LINENUMBER 773 L23
    LDC 32826
    INVOKESTATIC org/lwjgl/opengl/GL11.glEnable (I)V
    GOTO L24
   L22
    LINENUMBER 775 L22
   FRAME FULL [codechicken/nei/guihook/GuiContainerManager net/minecraft/inventory/Slot net/minecraft/item/ItemStack I I java/lang/String I F] []
    LDC 32826
    INVOKESTATIC org/lwjgl/opengl/GL11.glDisable (I)V
   L24
    LINENUMBER 777 L24
   FRAME FULL [codechicken/nei/guihook/GuiContainerManager net/minecraft/inventory/Slot net/minecraft/item/ItemStack I I java/lang/String I F] []
    GETSTATIC codechicken/nei/guihook/GuiContainerManager.drawItems : Lnet/minecraft/client/renderer/entity/RenderItem;
    FLOAD 7
    LDC 100.0
    FSUB
    PUTFIELD net/minecraft/client/renderer/entity/RenderItem.zLevel : F
   L25
    LINENUMBER 778 L25
    RETURN
   L26
    LOCALVARIABLE e Ljava/lang/Exception; L15 L21 8
    LOCALVARIABLE this Lcodechicken/nei/guihook/GuiContainerManager; L3 L26 0
    LOCALVARIABLE slot Lnet/minecraft/inventory/Slot; L3 L26 1
    LOCALVARIABLE stack Lnet/minecraft/item/ItemStack; L3 L26 2
    LOCALVARIABLE x I L3 L26 3
    LOCALVARIABLE y I L3 L26 4
    LOCALVARIABLE quantity Ljava/lang/String; L3 L26 5
    LOCALVARIABLE glRescale Z L4 L26 6
    LOCALVARIABLE zLevel F L5 L26 7
    MAXSTACK = 7
    MAXLOCALS = 9

  // access flags 0x1
  public handleSlotClick(III)V
   L0
    LINENUMBER 784 L0
    ILOAD 1
    ICONST_M1
    IF_ICMPNE L1
    RETURN
   L1
    LINENUMBER 786 L1
   FRAME FULL [codechicken/nei/guihook/GuiContainerManager I I I] []
    ALOAD 0
    GETFIELD codechicken/nei/guihook/GuiContainerManager.window : Lnet/minecraft/client/gui/inventory/GuiContainer;
    INSTANCEOF codechicken/nei/guihook/IGuiClientSide
    IFEQ L2
   L3
    LINENUMBER 788 L3
    ALOAD 0
    GETFIELD codechicken/nei/guihook/GuiContainerManager.window : Lnet/minecraft/client/gui/inventory/GuiContainer;
    GETFIELD net/minecraft/client/gui/inventory/GuiContainer.mc : Lnet/minecraft/client/Minecraft;
    GETFIELD net/minecraft/client/Minecraft.thePlayer : Lnet/minecraft/client/entity/EntityClientPlayerMP;
    GETFIELD net/minecraft/client/entity/EntityClientPlayerMP.openContainer : Lnet/minecraft/inventory/Container;
    ILOAD 1
    ILOAD 2
    ILOAD 3
    ALOAD 0
    GETFIELD codechicken/nei/guihook/GuiContainerManager.window : Lnet/minecraft/client/gui/inventory/GuiContainer;
    GETFIELD net/minecraft/client/gui/inventory/GuiContainer.mc : Lnet/minecraft/client/Minecraft;
    GETFIELD net/minecraft/client/Minecraft.thePlayer : Lnet/minecraft/client/entity/EntityClientPlayerMP;
    INVOKEVIRTUAL net/minecraft/inventory/Container.slotClick (IIILnet/minecraft/entity/player/EntityPlayer;)Lnet/minecraft/item/ItemStack;
    POP
    GOTO L4
   L2
    LINENUMBER 789 L2
   FRAME FULL [codechicken/nei/guihook/GuiContainerManager I I I] []
    ALOAD 0
    GETFIELD codechicken/nei/guihook/GuiContainerManager.window : Lnet/minecraft/client/gui/inventory/GuiContainer;
    GETFIELD net/minecraft/client/gui/inventory/GuiContainer.mc : Lnet/minecraft/client/Minecraft;
    GETFIELD net/minecraft/client/Minecraft.playerController : Lnet/minecraft/client/multiplayer/PlayerControllerMP;
    ALOAD 0
    GETFIELD codechicken/nei/guihook/GuiContainerManager.window : Lnet/minecraft/client/gui/inventory/GuiContainer;
    GETFIELD net/minecraft/client/gui/inventory/GuiContainer.inventorySlots : Lnet/minecraft/inventory/Container;
    GETFIELD net/minecraft/inventory/Container.windowId : I
    ILOAD 1
    ILOAD 2
    ILOAD 3
    ALOAD 0
    GETFIELD codechicken/nei/guihook/GuiContainerManager.window : Lnet/minecraft/client/gui/inventory/GuiContainer;
    GETFIELD net/minecraft/client/gui/inventory/GuiContainer.mc : Lnet/minecraft/client/Minecraft;
    GETFIELD net/minecraft/client/Minecraft.thePlayer : Lnet/minecraft/client/entity/EntityClientPlayerMP;
   L5
    LINENUMBER 790 L5
    INVOKEVIRTUAL net/minecraft/client/multiplayer/PlayerControllerMP.windowClick (IIIILnet/minecraft/entity/player/EntityPlayer;)Lnet/minecraft/item/ItemStack;
    POP
   L4
    LINENUMBER 791 L4
   FRAME FULL [codechicken/nei/guihook/GuiContainerManager I I I] []
    RETURN
   L6
    LOCALVARIABLE this Lcodechicken/nei/guihook/GuiContainerManager; L0 L6 0
    LOCALVARIABLE slotIndex I L0 L6 1
    LOCALVARIABLE button I L0 L6 2
    LOCALVARIABLE modifiers I L0 L6 3
    MAXSTACK = 6
    MAXLOCALS = 4

  // access flags 0x1
  public handleMouseWheel()V
   L0
    LINENUMBER 797 L0
    INVOKESTATIC org/lwjgl/input/Mouse.getEventDWheel ()I
    ISTORE 1
   L1
    LINENUMBER 798 L1
    ILOAD 1
    IFEQ L2
    ALOAD 0
    ILOAD 1
    IFLE L3
    ICONST_1
    GOTO L4
   L3
   FRAME FULL [codechicken/nei/guihook/GuiContainerManager I] [codechicken/nei/guihook/GuiContainerManager]
    ICONST_M1
   L4
   FRAME FULL [codechicken/nei/guihook/GuiContainerManager I] [codechicken/nei/guihook/GuiContainerManager I]
    INVOKEVIRTUAL codechicken/nei/guihook/GuiContainerManager.mouseScrolled (I)V
   L2
    LINENUMBER 799 L2
   FRAME FULL [codechicken/nei/guihook/GuiContainerManager I] []
    RETURN
   L5
    LOCALVARIABLE this Lcodechicken/nei/guihook/GuiContainerManager; L0 L5 0
    LOCALVARIABLE i I L1 L5 1
    MAXSTACK = 2
    MAXLOCALS = 2

  // access flags 0x100A
  private static synthetic lambda$renderToolTips$0(Ljava/lang/String;Ljava/lang/String;)I
   L0
    LINENUMBER 592 L0
    ALOAD 0
    LDC " - "
    INVOKEVIRTUAL java/lang/String.indexOf (Ljava/lang/String;)I
    ALOAD 1
    LDC " - "
    INVOKEVIRTUAL java/lang/String.indexOf (Ljava/lang/String;)I
    INVOKESTATIC java/lang/Integer.compare (II)I
    IRETURN
   L1
    LOCALVARIABLE a Ljava/lang/String; L0 L1 0
    LOCALVARIABLE b Ljava/lang/String; L0 L1 1
    MAXSTACK = 3
    MAXLOCALS = 2

  // access flags 0x1008
  static synthetic access$000()Lcodechicken/nei/ItemStackSet;
   L0
    LINENUMBER 50 L0
    GETSTATIC codechicken/nei/guihook/GuiContainerManager.renderingErrorItems : Lcodechicken/nei/ItemStackSet;
    ARETURN
    MAXSTACK = 1
    MAXLOCALS = 0

  // access flags 0x8
  static <clinit>()V
   L0
    LINENUMBER 62 L0
    NEW net/minecraft/client/renderer/entity/RenderItem
    DUP
    INVOKESPECIAL net/minecraft/client/renderer/entity/RenderItem.<init> ()V
    PUTSTATIC codechicken/nei/guihook/GuiContainerManager.drawItems : Lnet/minecraft/client/renderer/entity/RenderItem;
   L1
    LINENUMBER 63 L1
    NEW codechicken/nei/guihook/HideousLinkedList
    DUP
    NEW java/util/concurrent/CopyOnWriteArrayList
    DUP
    INVOKESPECIAL java/util/concurrent/CopyOnWriteArrayList.<init> ()V
    INVOKESPECIAL codechicken/nei/guihook/HideousLinkedList.<init> (Ljava/util/List;)V
    PUTSTATIC codechicken/nei/guihook/GuiContainerManager.tooltipHandlers : Ljava/util/LinkedList;
   L2
    LINENUMBER 65 L2
    NEW codechicken/nei/guihook/HideousLinkedList
    DUP
    NEW java/util/concurrent/CopyOnWriteArrayList
    DUP
    INVOKESPECIAL java/util/concurrent/CopyOnWriteArrayList.<init> ()V
    INVOKESPECIAL codechicken/nei/guihook/HideousLinkedList.<init> (Ljava/util/List;)V
    PUTSTATIC codechicken/nei/guihook/GuiContainerManager.inputHandlers : Ljava/util/LinkedList;
   L3
    LINENUMBER 67 L3
    NEW codechicken/nei/guihook/HideousLinkedList
    DUP
    NEW java/util/concurrent/CopyOnWriteArrayList
    DUP
    INVOKESPECIAL java/util/concurrent/CopyOnWriteArrayList.<init> ()V
    INVOKESPECIAL codechicken/nei/guihook/HideousLinkedList.<init> (Ljava/util/List;)V
    PUTSTATIC codechicken/nei/guihook/GuiContainerManager.drawHandlers : Ljava/util/LinkedList;
   L4
    LINENUMBER 69 L4
    NEW codechicken/nei/guihook/HideousLinkedList
    DUP
    NEW java/util/concurrent/CopyOnWriteArrayList
    DUP
    INVOKESPECIAL java/util/concurrent/CopyOnWriteArrayList.<init> ()V
    INVOKESPECIAL codechicken/nei/guihook/HideousLinkedList.<init> (Ljava/util/List;)V
    PUTSTATIC codechicken/nei/guihook/GuiContainerManager.objectHandlers : Ljava/util/LinkedList;
   L5
    LINENUMBER 71 L5
    NEW codechicken/nei/guihook/HideousLinkedList
    DUP
    NEW java/util/concurrent/CopyOnWriteArrayList
    DUP
    INVOKESPECIAL java/util/concurrent/CopyOnWriteArrayList.<init> ()V
    INVOKESPECIAL codechicken/nei/guihook/HideousLinkedList.<init> (Ljava/util/List;)V
    PUTSTATIC codechicken/nei/guihook/GuiContainerManager.slotClickHandlers : Ljava/util/LinkedList;
   L6
    LINENUMBER 75 L6
    NEW codechicken/nei/guihook/DefaultSlotClickHandler
    DUP
    INVOKESPECIAL codechicken/nei/guihook/DefaultSlotClickHandler.<init> ()V
    INVOKESTATIC codechicken/nei/guihook/GuiContainerManager.addSlotClickHandler (Lcodechicken/nei/guihook/IContainerSlotClickHandler;)V
   L7
    LINENUMBER 289 L7
    ICONST_M1
    PUTSTATIC codechicken/nei/guihook/GuiContainerManager.modelviewDepth : I
   L8
    LINENUMBER 290 L8
    NEW java/util/HashSet
    DUP
    INVOKESPECIAL java/util/HashSet.<init> ()V
    PUTSTATIC codechicken/nei/guihook/GuiContainerManager.stackTraces : Ljava/util/HashSet;
   L9
    LINENUMBER 291 L9
    NEW codechicken/nei/ItemStackSet
    DUP
    INVOKESPECIAL codechicken/nei/ItemStackSet.<init> ()V
    PUTSTATIC codechicken/nei/guihook/GuiContainerManager.renderingErrorItems : Lcodechicken/nei/ItemStackSet;
    RETURN
    MAXSTACK = 4
    MAXLOCALS = 0
}
